{"skeleton":{"hash":"mnc2ABsj46uX6dQIiax02kWwvR0","spine":"3.2.01","width":752,"height":1532.2,"images":""},"bones":[{"name":"root"},{"name":"cog","parent":"root","x":-21.24,"y":35.6,"color":"000000ff"},{"name":"body","parent":"cog","x":-0.19,"y":12.14},{"name":"torso","parent":"body","length":92.79,"rotation":90,"x":0.19,"y":6.68},{"name":"head","parent":"torso","length":142.51,"x":93.26,"y":0.33,"inheritScale":false},{"name":"antenna","parent":"head","length":83.36,"rotation":21.04,"x":28.97,"y":94.1,"color":"58ff2eff"},{"name":"clavicle1","parent":"torso","length":52.33,"rotation":52.89,"x":51.91,"y":7.63,"color":"ff3a41ff"},{"name":"arm1","parent":"clavicle1","length":37.71,"rotation":102.05,"x":56.37,"y":2.34,"inheritScale":false,"color":"ed5f61ff"},{"name":"clavicle2","parent":"torso","length":52.07,"rotation":-50.55,"x":51.93,"y":-9.16,"color":"ff3a41ff"},{"name":"arm2","parent":"clavicle2","length":41.39,"rotation":-125.55,"x":58.86,"y":0.27,"inheritScale":false,"color":"ed5f61ff"},{"name":"leg1","parent":"body","length":34.64,"rotation":-92.15,"x":-31.7,"y":17.23,"inheritScale":false},{"name":"shin1","parent":"leg1","length":29.97,"rotation":360,"x":33.28,"y":-0.18},{"name":"foot1","parent":"shin1","length":10.14,"rotation":1.9,"x":34.82,"y":0.05},{"name":"leg2","parent":"body","length":35.12,"rotation":-89.74,"x":24.45,"y":16.55,"inheritScale":false},{"name":"shin2","parent":"leg2","length":25.25,"rotation":360,"x":32.77,"y":1.04},{"name":"foot2","parent":"shin2","length":11.95,"rotation":360,"x":29.54,"y":0.89},{"name":"forearm1","parent":"arm1","length":34.75,"rotation":35.33,"x":34.93,"y":0.98,"color":"ed5f61ff"},{"name":"forearm2","parent":"arm2","length":31.94,"rotation":34.99,"x":43.07,"y":-1.39,"color":"ed5f61ff"},{"name":"hand1","parent":"forearm1","length":27.14,"rotation":4.42,"x":35.26,"y":0.16,"inheritScale":false,"color":"ed5f61ff"},{"name":"hand2","parent":"forearm2","length":24.87,"rotation":3.45,"x":31.83,"y":0.29,"inheritScale":false,"color":"ed5f61ff"},{"name":"influence_bone","parent":"cog","length":59.51,"rotation":89.99,"x":-0.5,"y":-37.91,"color":"000000ff"},{"name":"particles_foot_bone","parent":"body","x":-0.13,"y":-48.99,"color":"fff200ff"},{"name":"tail","parent":"head","length":58.31,"rotation":180,"x":58.88,"y":67.64,"inheritScale":false}],"slots":[{"name":"ponytail3","bone":"tail","attachment":"ponytail"},{"name":"arm2","bone":"arm2","attachment":"arm2"},{"name":"forearm2","bone":"forearm2","attachment":"forearm2_a"},{"name":"hand2","bone":"hand2","attachment":"hand2_h"},{"name":"cheer_flag","bone":"hand2"},{"name":"leg2","bone":"leg2","attachment":"leg2_a"},{"name":"shin2","bone":"shin2","attachment":"shin2"},{"name":"foot2","bone":"foot2","attachment":"foot2_a"},{"name":"leg1","bone":"leg1","attachment":"leg1_a"},{"name":"shin1","bone":"shin1","attachment":"shin1_a"},{"name":"foot1","bone":"foot1","attachment":"foot1_d"},{"name":"torso2_back","bone":"torso","attachment":"torso2"},{"name":"torso1","bone":"torso","attachment":"torso1"},{"name":"torso2","bone":"torso","attachment":"torso2"},{"name":"arm1","bone":"arm1","attachment":"arm1_a"},{"name":"cheer_glove","bone":"hand1"},{"name":"hand1","bone":"hand1","attachment":"hand1_a"},{"name":"forearm1","bone":"forearm1","attachment":"forearm1_a"},{"name":"head","bone":"head","attachment":"head"},{"name":"mouth","bone":"head","attachment":"mouth_a5"},{"name":"eyes","bone":"head","attachment":"eyes_h5"},{"name":"faceshield","bone":"head","attachment":"faceshield"},{"name":"antenna","bone":"antenna","attachment":"antenna"},{"name":"particle1","bone":"head","attachment":"particle1"},{"name":"particle9","bone":"head","attachment":"particle9"},{"name":"particle10","bone":"head","attachment":"particle10"},{"name":"particle2","bone":"hand1","attachment":"particle2"},{"name":"particle3","bone":"torso","attachment":"particle3"},{"name":"particle4","bone":"hand2","attachment":"particle4"},{"name":"particle5","bone":"foot1","attachment":"particle5"},{"name":"particle6","bone":"foot2","attachment":"particle6"},{"name":"particle7","bone":"root","attachment":"particle7"},{"name":"particle12","bone":"root","attachment":"particle12"},{"name":"particle13","bone":"root","attachment":"particle13"},{"name":"particle14","bone":"root","attachment":"particle14"},{"name":"particle15","bone":"root","attachment":"particle15"},{"name":"particle16","bone":"influence_bone","attachment":"particle16"},{"name":"particle8","bone":"torso","attachment":"particle8"},{"name":"appear_blue","bone":"influence_bone","attachment":"3"},{"name":"appear_mag","bone":"influence_bone","attachment":"1"}],"skins":{"default":{},"luna1":{"antenna":{"antenna":{"name":"normal/antenna","x":35.71,"y":-6.47,"rotation":-111.04,"width":71,"height":117}},"appear_blue":{"1":{"name":"normal1/appear_1","x":1104.64,"y":-21.75,"rotation":-89.99,"width":751,"height":751},"2":{"name":"normal1/appear_2","x":679.85,"y":-21.75,"rotation":-89.99,"width":751,"height":751},"3":{"name":"normal1/appear_3","x":390.16,"y":-21.75,"rotation":-89.99,"width":751,"height":751},"4":{"name":"normal1/appear_4","x":142.31,"y":-21.75,"rotation":-89.99,"width":752,"height":752},"5":{"name":"normal1/appear_5","x":142.31,"y":-21.75,"rotation":-89.99,"width":752,"height":752},"3_2":{"name":"normal1/appear_5","x":142.31,"y":-21.75,"rotation":-89.99,"width":752,"height":752},"6":{"name":"normal1/appear_6","x":142.31,"y":-21.75,"scaleX":1.05,"scaleY":1.05,"rotation":-89.99,"width":752,"height":752},"7":{"name":"normal1/appear_7","x":142.31,"y":-21.75,"scaleX":1.1,"scaleY":1.1,"rotation":-89.99,"width":752,"height":752},"8":{"name":"normal1/appear_8","x":142.31,"y":-21.75,"scaleX":1.4,"scaleY":1.4,"rotation":-89.99,"width":752,"height":752},"9":{"name":"normal1/appear_9","x":142.31,"y":-21.75,"scaleX":1.6,"scaleY":1.6,"rotation":-89.99,"width":752,"height":752},"10":{"name":"normal1/appear_10","x":142.31,"y":-21.75,"scaleX":1.85,"scaleY":1.85,"rotation":-89.99,"width":752,"height":752},"11":{"name":"normal1/appear_11","x":142.31,"y":-21.75,"scaleX":1.95,"scaleY":1.95,"rotation":-89.99,"width":752,"height":752}},"appear_mag":{"1":{"name":"normal1/mag_appear_1","x":1104.64,"y":-21.75,"rotation":-89.99,"width":752,"height":752},"2":{"name":"normal1/mag_appear_2","x":679.85,"y":-21.75,"rotation":-89.99,"width":752,"height":752},"3":{"name":"normal1/mag_appear_3","x":390.16,"y":-21.75,"rotation":-89.99,"width":752,"height":752},"4":{"name":"normal1/mag_appear_4","x":142.31,"y":-21.75,"rotation":-89.99,"width":752,"height":752},"5":{"name":"normal1/mag_appear_5","x":142.31,"y":-21.75,"rotation":-89.99,"width":752,"height":752},"3_2":{"name":"normal1/mag_appear_5","x":142.31,"y":-21.75,"rotation":-89.99,"width":752,"height":752},"6":{"name":"normal1/mag_appear_6","x":142.31,"y":-21.75,"scaleX":1.05,"scaleY":1.05,"rotation":-89.99,"width":752,"height":752},"7":{"name":"normal1/mag_appear_7","x":142.31,"y":-21.75,"scaleX":1.1,"scaleY":1.1,"rotation":-89.99,"width":752,"height":752},"8":{"name":"normal1/mag_appear_8","x":142.31,"y":-21.75,"scaleX":1.4,"scaleY":1.4,"rotation":-89.99,"width":752,"height":752},"9":{"name":"normal1/mag_appear_9","x":142.31,"y":-21.75,"scaleX":1.6,"scaleY":1.6,"rotation":-89.99,"width":752,"height":752},"10":{"name":"normal1/mag_appear_10","x":142.31,"y":-21.75,"scaleX":1.85,"scaleY":1.85,"rotation":-89.99,"width":752,"height":752},"11":{"name":"normal1/mag_appear_11","x":142.31,"y":-21.75,"scaleX":1.95,"scaleY":1.95,"rotation":-89.99,"width":752,"height":752}},"arm1":{"arm1_a":{"name":"normal/arm1_a","x":21.93,"y":3.59,"rotation":129.59,"width":48,"height":59}},"arm2":{"arm2":{"name":"normal/arm2_a","x":28.86,"y":4.17,"rotation":80.96,"width":36,"height":53},"arm3":{"name":"normal/arm2_a","x":23.96,"y":1.23,"scaleX":-1,"rotation":109.63,"width":36,"height":53}},"cheer_flag":{"cheer_flag":{"name":"normal1/cheer_flag","x":94.43,"y":121.37,"rotation":12.01,"width":220,"height":256}},"cheer_glove":{"cheer_glove":{"name":"normal1/cheer_glove","x":89.42,"y":1.92,"rotation":-91.43,"width":188,"height":256}},"eyes":{"eyes_a1":{"name":"normal/eyes_a1","x":40.14,"y":-24.53,"rotation":-90,"width":151,"height":54},"eyes_b1":{"name":"normal/eyes_b1","x":34.4,"y":-24.6,"rotation":270,"width":149,"height":50},"eyes_b2":{"name":"normal/eyes_b2","x":39.26,"y":-21.06,"rotation":-90,"width":141,"height":55},"eyes_b3":{"name":"normal/eyes_b3","x":35.15,"y":-23.39,"rotation":-90.28,"width":148,"height":49},"eyes_c1":{"name":"normal/eyes_c1","x":42.09,"y":-19.89,"rotation":-90,"width":143,"height":56},"eyes_c2":{"name":"normal/eyes_c2","x":37.6,"y":-23.18,"rotation":-90,"width":142,"height":55},"eyes_d1":{"name":"normal/eyes_d1","x":34.79,"y":-22.92,"rotation":-90,"width":150,"height":45},"eyes_d2":{"name":"normal/eyes_d2","x":38.49,"y":-22.8,"rotation":-90,"width":151,"height":51},"eyes_d3":{"name":"normal/eyes_d3","x":39.34,"y":-22.15,"rotation":-90,"width":145,"height":56},"eyes_e1":{"name":"normal/eyes_e1","x":44.85,"y":-22.07,"rotation":-90,"width":145,"height":67},"eyes_e2":{"name":"normal/eyes_e2","x":43.66,"y":-20.88,"rotation":-90,"width":145,"height":67},"eyes_f1":{"name":"normal/eyes_f1","x":44.97,"y":-27.07,"rotation":-90,"width":141,"height":80},"eyes_f2":{"name":"normal/eyes_f2","x":44.2,"y":-29.83,"rotation":-90,"width":152,"height":99},"eyes_g1":{"name":"normal/eyes_g1","x":39.65,"y":-25.12,"rotation":-90,"width":147,"height":56},"eyes_g2":{"name":"normal/eyes_g2","x":39.95,"y":-25.42,"rotation":-90,"width":148,"height":56},"eyes_h1":{"name":"normal/eyes_h1","x":42.66,"y":-28.45,"rotation":-90,"width":142,"height":47},"eyes_h2":{"name":"normal/eyes_h2","x":48.06,"y":-22.09,"rotation":270,"width":139,"height":67},"eyes_h3":{"name":"normal/eyes_h3","x":40.55,"y":-22.97,"rotation":-90,"width":140,"height":52},"eyes_h4":{"name":"normal/eyes_h4","x":43.17,"y":-20.57,"rotation":-90,"width":143,"height":53},"eyes_h5":{"name":"normal/eyes_h5","x":37.5,"y":-20.57,"rotation":-90,"width":140,"height":53},"eyes_i1":{"name":"normal/eyes_i1","x":44.3,"y":-20.57,"rotation":-90,"width":144,"height":84},"eyes_i2":{"name":"normal/eyes_i2","x":44.3,"y":-21.67,"rotation":-90,"width":144,"height":85},"eyes_i3":{"name":"normal/eyes_i3","x":44.3,"y":-20.57,"rotation":-90,"width":144,"height":84},"eyes_i4":{"name":"normal/eyes_i4","x":44.3,"y":-20.57,"rotation":-90,"width":144,"height":85}},"faceshield":{"faceshield":{"name":"normal/faceshield","x":61.98,"y":-17.76,"rotation":-90,"width":202,"height":178}},"foot1":{"foot1_a":{"name":"normal/foot1_a","x":0.76,"y":9.19,"rotation":88.45,"width":60,"height":16},"foot1_a_i":{"name":"normal/foot1_a","x":0.76,"y":9.19,"rotation":88.45,"width":60,"height":16},"foot1_b":{"name":"normal/foot1_b","x":-3.42,"y":7.71,"rotation":88.45,"width":59,"height":17},"foot1_c":{"name":"normal/foot1_c","x":-14.73,"y":-2.61,"rotation":88.45,"width":45,"height":55},"foot1_d":{"name":"normal/foot1_d","x":-7.28,"y":5.37,"rotation":88.45,"width":65,"height":34},"foot1_e":{"name":"normal/foot1_e","x":5.67,"y":4.19,"rotation":88.45,"width":58,"height":29},"foot1_f":{"name":"normal/foot1_f","x":-6.66,"y":9.92,"rotation":1.65,"width":36,"height":52},"foot1_g":{"name":"normal/foot1_g","x":-6.36,"y":9.91,"rotation":17.52,"width":41,"height":50}},"foot2":{"foot2_a":{"name":"normal/foot2_a","x":1.38,"y":3.69,"rotation":90,"width":53,"height":15},"foot2_a_i":{"name":"normal/foot2_a","x":1.38,"y":3.69,"rotation":90,"width":53,"height":15},"foot2_b":{"name":"normal/foot2_b","x":-2.22,"y":1.8,"rotation":90,"width":51,"height":15},"foot2_c":{"name":"normal/foot2_c","x":-9.13,"y":-8.22,"rotation":90,"width":39,"height":47},"foot2_d":{"name":"normal/foot2_d","x":-3.62,"y":-0.87,"rotation":90,"width":55,"height":29},"foot2_e":{"name":"normal/foot2_e","x":5.42,"y":-0.7,"rotation":90,"width":53,"height":26}},"forearm1":{"forearm1_a":{"name":"normal/forearm1_a","x":20.5,"y":0.65,"rotation":87.96,"width":50,"height":55}},"forearm2":{"forearm2_a":{"name":"normal/forearm2_a","x":22.83,"y":2.7,"rotation":55.94,"width":53,"height":55}},"hand1":{"hand1_a":{"name":"normal/hand1_a","x":12.42,"y":0.94,"rotation":83.54,"width":54,"height":43},"hand1_b":{"name":"normal/hand1_b","x":13.12,"y":-1.59,"rotation":83.54,"width":49,"height":49},"hand1_c":{"name":"normal/hand1_c","x":15.64,"y":-1.87,"rotation":83.54,"width":50,"height":53},"hand1_d":{"name":"normal/hand1_d","x":10.9,"y":4.73,"rotation":83.54,"width":63,"height":45},"hand1_e":{"name":"normal/hand1_e","x":13.82,"y":-2.42,"rotation":83.54,"width":65,"height":52},"hand1_f":{"name":"normal/hand1_f","x":10.72,"y":4.2,"rotation":83.54,"width":57,"height":31},"hand1_g":{"name":"normal/hand1_g","x":12.82,"y":1.36,"rotation":92.58,"width":51,"height":33},"hand1_h":{"name":"normal/hand1_h","x":15.41,"y":-1.85,"rotation":83.54,"width":44,"height":54},"hand1_i":{"name":"normal/hand1_i","x":19.18,"y":-4.28,"rotation":83.54,"width":55,"height":46}},"hand2":{"hand2_a":{"name":"normal/hand2_a","x":14.15,"y":1.29,"rotation":53.27,"width":44,"height":28},"hand2_b":{"name":"normal/hand2_b","x":16,"y":-1.15,"rotation":53.27,"width":42,"height":39},"hand2_c":{"name":"normal/hand2_c","x":13.35,"y":0.86,"rotation":53.27,"width":43,"height":37},"hand2_d":{"name":"normal/hand2_d","x":15.71,"y":2.88,"rotation":53.27,"width":49,"height":37},"hand2_e":{"name":"normal/hand2_e","x":15.95,"y":1.89,"rotation":53.27,"width":45,"height":38},"hand2_f":{"name":"normal/hand2_f","x":10.07,"y":6.38,"rotation":57.45,"width":48,"height":33},"hand2_g":{"name":"normal/hand2_g","x":11.34,"y":-2.86,"rotation":67.2,"width":41,"height":39},"hand2_h":{"name":"normal/hand2_h","x":22.56,"y":1.24,"rotation":38.52,"width":53,"height":40}},"head":{"head":{"name":"normal/head","x":92.25,"y":5.99,"rotation":-90,"width":253,"height":237}},"leg1":{"leg1_a":{"name":"normal/leg1_a","x":22.09,"y":4.77,"rotation":90,"width":63,"height":73},"leg1_i":{"name":"normal/leg1_a","x":16.05,"y":3.33,"rotation":90,"width":63,"height":73},"leg1_b":{"name":"normal/leg1_b","x":10.18,"y":6.09,"rotation":17.47,"width":89,"height":73},"leg1_c":{"name":"normal/leg1_c","x":26.01,"y":2.95,"rotation":25.28,"width":62,"height":54}},"leg2":{"leg2_a":{"name":"normal/leg2_a","x":16.68,"y":0.61,"rotation":89.74,"width":57,"height":65},"leg2_i":{"name":"normal/leg2_a","x":16.68,"y":0.61,"rotation":89.74,"width":57,"height":65}},"mouth":{"mouth_a1":{"name":"normal/mouth_a1","x":-4.22,"y":-36.13,"rotation":-90,"width":40,"height":10},"mouth_a2":{"name":"normal/mouth_a2","x":-3.31,"y":-37.08,"rotation":-90,"width":32,"height":10},"mouth_a3":{"name":"normal/mouth_a3","x":-2.1,"y":-35.87,"rotation":-90,"width":43,"height":15},"mouth_a4":{"name":"normal/mouth_a4","x":-2.71,"y":-37.38,"rotation":-90,"width":47,"height":18},"mouth_a5":{"name":"normal/mouth_a5","x":-3.01,"y":-39.5,"rotation":-90,"width":42,"height":14},"mouth_a6":{"name":"normal/mouth_a6","x":-3.31,"y":-23.36,"rotation":-90,"width":22,"height":12},"mouth_a7":{"name":"normal/mouth_a7","x":-1.8,"y":-29.69,"rotation":-90,"width":23,"height":12},"mouth_a8":{"name":"normal/mouth_a8","x":-1.49,"y":-36.17,"rotation":-90,"width":19,"height":22},"mouth_b1":{"name":"normal/mouth_b1","x":-2.1,"y":-34.05,"rotation":-90,"width":53,"height":26},"mouth_b2":{"name":"normal/mouth_b2","x":-3.01,"y":-36.17,"rotation":-90,"width":48,"height":18},"mouth_b3":{"name":"normal/mouth_b3","x":-3.01,"y":-30.31,"rotation":-90,"width":61,"height":22},"mouth_b4":{"name":"normal/mouth_b4","x":-1.73,"y":-34.36,"rotation":-90,"width":51,"height":20},"mouth_b5":{"name":"normal/mouth_b5","x":-1.49,"y":-38.29,"rotation":-90,"width":47,"height":14},"mouth_b6":{"name":"normal/mouth_b6","x":-2.4,"y":-37.69,"rotation":-90,"width":35,"height":15},"mouth_b7":{"name":"normal/mouth_b7","x":-1.49,"y":-35.05,"rotation":-90.07,"width":57,"height":20},"mouth_c1":{"name":"normal/mouth_c1","x":-0.28,"y":-38.6,"rotation":-90,"width":17,"height":24},"mouth_c2":{"name":"normal/mouth_c2","x":-0.89,"y":-40.41,"rotation":-90,"width":21,"height":29},"mouth_c3":{"name":"normal/mouth_c3","x":0.62,"y":-40.11,"rotation":-89.91,"width":23,"height":32},"mouth_d1":{"name":"normal/mouth_d1","x":-1.19,"y":-34.96,"rotation":-90,"width":58,"height":33},"mouth_d2":{"name":"normal/mouth_d2","x":0.01,"y":-33.75,"rotation":-90,"width":56,"height":28},"mouth_d3":{"name":"normal/mouth_d3","x":-1.8,"y":-32.54,"rotation":270,"width":69,"height":31},"mouth_d4":{"name":"normal/mouth_d4","x":-2.1,"y":-33.15,"rotation":-90,"width":56,"height":28},"mouth_d5":{"name":"normal/mouth_d5","x":-0.59,"y":-34.96,"rotation":-90,"width":51,"height":32},"mouth_d6":{"name":"normal/mouth_d6","x":-0.28,"y":-33.75,"rotation":-90,"width":42,"height":31},"mouth_d7":{"name":"normal/mouth_d7","x":-1.19,"y":-32.54,"rotation":-90,"width":53,"height":30},"mouth_d8":{"name":"normal/mouth_d8","x":-1.8,"y":-32.24,"rotation":-90,"width":65,"height":31},"mouth_d9":{"name":"normal/mouth_d9","x":-1.19,"y":-37.08,"rotation":-90,"width":38,"height":44}},"particle1":{"particle1":{"name":"normal/particle","x":188.66,"y":-8.63,"rotation":-90,"width":104,"height":104}},"particle10":{"particle10":{"name":"normal/particle","x":75.28,"y":-92.04,"rotation":-90,"width":104,"height":104}},"particle12":{"particle12":{"name":"normal/particle","x":155,"width":104,"height":104}},"particle13":{"particle13":{"name":"normal/particle","x":285.5,"y":689.22,"width":104,"height":104}},"particle14":{"particle14":{"name":"normal/particle","x":175.22,"y":551.01,"width":104,"height":104}},"particle15":{"particle15":{"name":"normal/particle","x":29.88,"y":662.2,"width":104,"height":104}},"particle16":{"particle16":{"name":"normal/particle","x":119.68,"y":-19.97,"rotation":-90,"width":104,"height":104}},"particle2":{"particle2":{"name":"normal/particle","x":14.93,"y":-2.91,"rotation":75.29,"width":104,"height":104}},"particle3":{"particle3":{"name":"normal/particle","x":2.14,"y":36.89,"rotation":-90,"width":104,"height":104}},"particle4":{"particle4":{"name":"normal/particle","x":13.37,"y":-4.16,"rotation":47.66,"width":104,"height":104}},"particle5":{"particle5":{"name":"normal/particle","x":-1.23,"y":7.54,"rotation":90.24,"width":104,"height":104}},"particle6":{"particle6":{"name":"normal/particle","x":3.86,"y":-0.19,"rotation":89.74,"width":104,"height":104}},"particle7":{"particle7":{"name":"normal/particle","x":-19.62,"y":-1.86,"width":104,"height":104}},"particle8":{"particle8":{"name":"normal/particle","x":40.01,"y":-1.62,"rotation":-90,"width":104,"height":104}},"particle9":{"particle9":{"name":"normal/particle","x":76.09,"y":105.55,"rotation":-90,"width":104,"height":104}},"ponytail3":{"ponytail":{"name":"normal/ponytail3","x":52.88,"y":-8.13,"rotation":90,"width":94,"height":116}},"shin1":{"shin1_a":{"name":"normal/shin1_a","x":20.57,"y":4.44,"rotation":90,"width":62,"height":41},"shin1_i":{"name":"normal/shin1_a","x":20.57,"y":4.44,"rotation":90,"width":62,"height":41},"shin1_b":{"name":"normal/shin1_b","x":13.16,"y":6.51,"rotation":10.32,"width":50,"height":56}},"shin2":{"shin2":{"name":"normal/shin2_a","x":17.98,"y":0.5,"rotation":90,"width":55,"height":37},"shin2_i":{"name":"normal/shin2_a","x":17.98,"y":0.5,"rotation":90,"width":55,"height":37}},"torso1":{"torso1":{"name":"normal/torso1","x":79.78,"y":-3.31,"rotation":-90,"width":105,"height":87}},"torso2_back":{"torso2":{"name":"normal/torso2","x":38.47,"y":0.76,"rotation":-90,"width":113,"height":98}}},"luna2":{"antenna":{"antenna":{"name":"normal2/antenna","x":35.71,"y":-6.47,"rotation":-111.04,"width":83,"height":131}},"appear_blue":{"1":{"name":"normal1/appear_1","x":1104.64,"y":-21.75,"rotation":-89.99,"width":751,"height":751},"2":{"name":"normal1/appear_2","x":679.85,"y":-21.75,"rotation":-89.99,"width":751,"height":751},"3":{"name":"normal1/appear_3","x":390.16,"y":-21.75,"rotation":-89.99,"width":751,"height":751},"4":{"name":"normal1/appear_4","x":142.31,"y":-21.75,"rotation":-89.99,"width":752,"height":752},"5":{"name":"normal1/appear_5","x":142.31,"y":-21.75,"rotation":-89.99,"width":752,"height":752},"3_2":{"name":"normal1/appear_5","x":142.31,"y":-21.75,"rotation":-89.99,"width":752,"height":752},"6":{"name":"normal1/appear_6","x":142.31,"y":-21.75,"scaleX":1.05,"scaleY":1.05,"rotation":-89.99,"width":752,"height":752},"7":{"name":"normal1/appear_7","x":142.31,"y":-21.75,"scaleX":1.1,"scaleY":1.1,"rotation":-89.99,"width":752,"height":752},"8":{"name":"normal1/appear_8","x":142.31,"y":-21.75,"scaleX":1.4,"scaleY":1.4,"rotation":-89.99,"width":752,"height":752},"9":{"name":"normal1/appear_9","x":142.31,"y":-21.75,"scaleX":1.6,"scaleY":1.6,"rotation":-89.99,"width":752,"height":752},"10":{"name":"normal1/appear_10","x":142.31,"y":-21.75,"scaleX":1.85,"scaleY":1.85,"rotation":-89.99,"width":752,"height":752},"11":{"name":"normal1/appear_11","x":142.31,"y":-21.75,"scaleX":1.95,"scaleY":1.95,"rotation":-89.99,"width":752,"height":752}},"appear_mag":{"1":{"name":"normal1/mag_appear_1","x":1104.64,"y":-21.75,"rotation":-89.99,"width":752,"height":752},"2":{"name":"normal1/mag_appear_2","x":679.85,"y":-21.75,"rotation":-89.99,"width":752,"height":752},"3":{"name":"normal1/mag_appear_3","x":390.16,"y":-21.75,"rotation":-89.99,"width":752,"height":752},"4":{"name":"normal1/mag_appear_4","x":142.31,"y":-21.75,"rotation":-89.99,"width":752,"height":752},"5":{"name":"normal1/mag_appear_5","x":142.31,"y":-21.75,"rotation":-89.99,"width":752,"height":752},"3_2":{"name":"normal1/mag_appear_5","x":142.31,"y":-21.75,"rotation":-89.99,"width":752,"height":752},"6":{"name":"normal1/mag_appear_6","x":142.31,"y":-21.75,"scaleX":1.05,"scaleY":1.05,"rotation":-89.99,"width":752,"height":752},"7":{"name":"normal1/mag_appear_7","x":142.31,"y":-21.75,"scaleX":1.1,"scaleY":1.1,"rotation":-89.99,"width":752,"height":752},"8":{"name":"normal1/mag_appear_8","x":142.31,"y":-21.75,"scaleX":1.4,"scaleY":1.4,"rotation":-89.99,"width":752,"height":752},"9":{"name":"normal1/mag_appear_9","x":142.31,"y":-21.75,"scaleX":1.6,"scaleY":1.6,"rotation":-89.99,"width":752,"height":752},"10":{"name":"normal1/mag_appear_10","x":142.31,"y":-21.75,"scaleX":1.85,"scaleY":1.85,"rotation":-89.99,"width":752,"height":752},"11":{"name":"normal1/mag_appear_11","x":142.31,"y":-21.75,"scaleX":1.95,"scaleY":1.95,"rotation":-89.99,"width":752,"height":752}},"arm1":{"arm1_a":{"name":"normal2/arm1_a","x":21.93,"y":3.59,"rotation":129.59,"width":48,"height":59}},"arm2":{"arm2":{"name":"normal2/arm2_a","x":28.86,"y":4.17,"rotation":80.96,"width":36,"height":53},"arm3":{"name":"normal2/arm2_a","x":23.96,"y":1.23,"scaleX":-1,"rotation":109.63,"width":36,"height":53}},"cheer_flag":{"cheer_flag":{"name":"normal1/cheer_flag","x":94.43,"y":121.37,"rotation":12.01,"width":220,"height":256}},"cheer_glove":{"cheer_glove":{"name":"normal1/cheer_glove","x":89.42,"y":1.92,"rotation":-91.43,"width":188,"height":256}},"eyes":{"eyes_a1":{"name":"normal2/eyes_a1","x":40.14,"y":-24.53,"rotation":-90,"width":151,"height":54},"eyes_b1":{"name":"normal2/eyes_b1","x":34.4,"y":-24.6,"rotation":270,"width":149,"height":50},"eyes_b2":{"name":"normal2/eyes_b2","x":39.26,"y":-21.06,"rotation":-90,"width":141,"height":55},"eyes_b3":{"name":"normal2/eyes_b3","x":35.15,"y":-23.39,"rotation":-90.28,"width":148,"height":49},"eyes_c1":{"name":"normal2/eyes_c1","x":42.09,"y":-19.89,"rotation":-90,"width":143,"height":56},"eyes_c2":{"name":"normal2/eyes_c2","x":37.6,"y":-23.18,"rotation":-90,"width":142,"height":55},"eyes_d1":{"name":"normal2/eyes_d1","x":34.79,"y":-22.92,"rotation":-90,"width":150,"height":45},"eyes_d2":{"name":"normal2/eyes_d2","x":38.49,"y":-22.8,"rotation":-90,"width":151,"height":51},"eyes_d3":{"name":"normal2/eyes_d3","x":39.34,"y":-22.15,"rotation":-90,"width":145,"height":56},"eyes_e1":{"name":"normal2/eyes_e1","x":44.85,"y":-22.07,"rotation":-90,"width":145,"height":67},"eyes_e2":{"name":"normal2/eyes_e2","x":43.66,"y":-20.88,"rotation":-90,"width":145,"height":67},"eyes_f1":{"name":"normal2/eyes_f1","x":44.97,"y":-27.07,"rotation":-90,"width":141,"height":80},"eyes_f2":{"name":"normal2/eyes_f2","x":44.2,"y":-29.83,"rotation":-90,"width":152,"height":99},"eyes_g1":{"name":"normal2/eyes_g1","x":39.65,"y":-25.12,"rotation":-90,"width":147,"height":56},"eyes_g2":{"name":"normal2/eyes_g2","x":39.95,"y":-25.42,"rotation":-90,"width":148,"height":56},"eyes_h1":{"name":"normal2/eyes_h1","x":42.66,"y":-28.45,"rotation":-90,"width":142,"height":47},"eyes_h2":{"name":"normal2/eyes_h2","x":48.06,"y":-22.09,"rotation":270,"width":139,"height":67},"eyes_h3":{"name":"normal2/eyes_h3","x":40.55,"y":-22.97,"rotation":-90,"width":140,"height":52},"eyes_h4":{"name":"normal2/eyes_h4","x":43.17,"y":-20.57,"rotation":-90,"width":143,"height":53},"eyes_h5":{"name":"normal2/eyes_h5","x":37.5,"y":-20.57,"rotation":-90,"width":140,"height":53},"eyes_i1":{"name":"normal2/eyes_i1","x":44.3,"y":-20.57,"rotation":-90,"width":144,"height":84},"eyes_i2":{"name":"normal2/eyes_i2","x":44.3,"y":-21.67,"rotation":-90,"width":144,"height":85},"eyes_i3":{"name":"normal2/eyes_i3","x":44.3,"y":-20.57,"rotation":-90,"width":144,"height":84},"eyes_i4":{"name":"normal2/eyes_i4","x":44.3,"y":-20.57,"rotation":-90,"width":144,"height":85}},"faceshield":{"faceshield":{"name":"normal2/faceshield","x":61.98,"y":-17.76,"rotation":-90,"width":216,"height":144}},"foot1":{"foot1_a":{"name":"normal2/foot1_a","x":0.76,"y":9.19,"rotation":88.45,"width":60,"height":16},"foot1_a_i":{"name":"normal2/foot1_a","x":0.76,"y":9.19,"rotation":88.45,"width":60,"height":16},"foot1_b":{"name":"normal2/foot1_b","x":-3.42,"y":7.71,"rotation":88.45,"width":59,"height":17},"foot1_c":{"name":"normal2/foot1_c","x":-14.73,"y":-2.61,"rotation":88.45,"width":45,"height":55},"foot1_d":{"name":"normal2/foot1_d","x":-7.28,"y":5.37,"rotation":88.45,"width":65,"height":34},"foot1_e":{"name":"normal2/foot1_e","x":5.67,"y":4.19,"rotation":88.45,"width":58,"height":29},"foot1_f":{"name":"normal2/foot1_f","x":-6.66,"y":9.92,"rotation":1.65,"width":36,"height":53},"foot1_g":{"name":"normal2/foot1_g","x":-6.36,"y":9.91,"rotation":17.52,"width":40,"height":50}},"foot2":{"foot2_a":{"name":"normal2/foot2_a","x":1.38,"y":3.69,"rotation":90,"width":53,"height":15},"foot2_a_i":{"name":"normal2/foot2_a","x":1.38,"y":3.69,"rotation":90,"width":53,"height":15},"foot2_b":{"name":"normal2/foot2_b","x":-2.22,"y":1.8,"rotation":90,"width":51,"height":15},"foot2_c":{"name":"normal2/foot2_c","x":-9.13,"y":-8.22,"rotation":90,"width":39,"height":47},"foot2_d":{"name":"normal2/foot2_d","x":-3.62,"y":-0.87,"rotation":90,"width":55,"height":29},"foot2_e":{"name":"normal2/foot2_e","x":5.42,"y":-0.7,"rotation":90,"width":53,"height":26}},"forearm1":{"forearm1_a":{"name":"normal2/forearm1_a","x":20.5,"y":0.65,"rotation":87.96,"width":50,"height":55}},"forearm2":{"forearm2_a":{"name":"normal2/forearm2_a","x":22.83,"y":2.7,"rotation":55.94,"width":53,"height":55}},"hand1":{"hand1_a":{"name":"normal2/hand1_a","x":12.42,"y":0.94,"rotation":83.54,"width":54,"height":43},"hand1_b":{"name":"normal2/hand1_b","x":13.12,"y":-1.59,"rotation":83.54,"width":49,"height":49},"hand1_c":{"name":"normal2/hand1_c","x":15.64,"y":-1.87,"rotation":83.54,"width":50,"height":53},"hand1_d":{"name":"normal2/hand1_d","x":10.9,"y":4.73,"rotation":83.54,"width":63,"height":45},"hand1_e":{"name":"normal2/hand1_e","x":13.82,"y":-2.42,"rotation":83.54,"width":65,"height":52},"hand1_f":{"name":"normal2/hand1_f","x":10.72,"y":4.2,"rotation":83.54,"width":57,"height":31},"hand1_g":{"name":"normal2/hand1_g","x":12.82,"y":1.36,"rotation":92.58,"width":51,"height":33},"hand1_h":{"name":"normal2/hand1_h","x":15.41,"y":-1.85,"rotation":83.54,"width":44,"height":54},"hand1_i":{"name":"normal2/hand1_i","x":19.18,"y":-4.28,"rotation":83.54,"width":55,"height":46}},"hand2":{"hand2_a":{"name":"normal2/hand2_a","x":14.15,"y":1.29,"rotation":53.27,"width":44,"height":28},"hand2_b":{"name":"normal2/hand2_b","x":16,"y":-1.15,"rotation":53.27,"width":42,"height":39},"hand2_c":{"name":"normal2/hand2_c","x":13.35,"y":0.86,"rotation":53.27,"width":43,"height":37},"hand2_d":{"name":"normal2/hand2_d","x":15.71,"y":2.88,"rotation":53.27,"width":49,"height":37},"hand2_e":{"name":"normal2/hand2_e","x":15.95,"y":1.89,"rotation":53.27,"width":45,"height":38},"hand2_f":{"name":"normal2/hand2_f","x":10.07,"y":6.38,"rotation":57.45,"width":48,"height":33},"hand2_g":{"name":"normal2/hand2_g","x":11.34,"y":-2.86,"rotation":67.2,"width":41,"height":39},"hand2_h":{"name":"normal2/hand2_h","x":22.56,"y":1.24,"rotation":38.52,"width":53,"height":40}},"head":{"head":{"name":"normal2/head","x":92.25,"y":5.99,"rotation":-90,"width":254,"height":237}},"leg1":{"leg1_a":{"name":"normal2/leg1_a","x":22.09,"y":4.77,"rotation":90,"width":63,"height":73},"leg1_i":{"name":"normal2/leg1_a","x":16.05,"y":3.33,"rotation":90,"width":63,"height":73},"leg1_b":{"name":"normal2/leg1_b","x":10.18,"y":6.09,"rotation":17.47,"width":97,"height":73},"leg1_c":{"name":"normal2/leg1_c","x":26.01,"y":2.95,"rotation":25.28,"width":59,"height":57}},"leg2":{"leg2_a":{"name":"normal2/leg2_a","x":16.68,"y":0.61,"rotation":89.74,"width":57,"height":65},"leg2_i":{"name":"normal2/leg2_a","x":16.68,"y":0.61,"rotation":89.74,"width":57,"height":65}},"mouth":{"mouth_a1":{"name":"normal2/mouth_a1","x":-4.22,"y":-36.13,"rotation":-90,"width":40,"height":10},"mouth_a2":{"name":"normal2/mouth_a2","x":-3.31,"y":-37.08,"rotation":-90,"width":32,"height":10},"mouth_a3":{"name":"normal2/mouth_a3","x":-2.1,"y":-35.87,"rotation":-90,"width":43,"height":15},"mouth_a4":{"name":"normal2/mouth_a4","x":-2.71,"y":-37.38,"rotation":-90,"width":47,"height":18},"mouth_a5":{"name":"normal2/mouth_a5","x":-3.01,"y":-39.5,"rotation":-90,"width":42,"height":14},"mouth_a6":{"name":"normal2/mouth_a6","x":-3.31,"y":-23.36,"rotation":-90,"width":22,"height":12},"mouth_a7":{"name":"normal2/mouth_a7","x":-1.8,"y":-29.69,"rotation":-90,"width":23,"height":12},"mouth_a8":{"name":"normal2/mouth_a8","x":-1.49,"y":-36.17,"rotation":-90,"width":19,"height":22},"mouth_b1":{"name":"normal2/mouth_b1","x":-2.1,"y":-34.05,"rotation":-90,"width":53,"height":26},"mouth_b2":{"name":"normal2/mouth_b2","x":-3.01,"y":-36.17,"rotation":-90,"width":48,"height":18},"mouth_b3":{"name":"normal2/mouth_b3","x":-3.01,"y":-30.31,"rotation":-90,"width":61,"height":22},"mouth_b4":{"name":"normal2/mouth_b4","x":-1.73,"y":-34.36,"rotation":-90,"width":51,"height":20},"mouth_b5":{"name":"normal2/mouth_b5","x":-1.49,"y":-38.29,"rotation":-90,"width":47,"height":14},"mouth_b6":{"name":"normal2/mouth_b6","x":-2.4,"y":-37.69,"rotation":-90,"width":35,"height":15},"mouth_b7":{"name":"normal2/mouth_b7","x":-1.49,"y":-35.05,"rotation":-90.07,"width":57,"height":20},"mouth_c1":{"name":"normal2/mouth_c1","x":-0.28,"y":-38.6,"rotation":-90,"width":17,"height":24},"mouth_c2":{"name":"normal2/mouth_c2","x":-0.89,"y":-40.41,"rotation":-90,"width":21,"height":29},"mouth_c3":{"name":"normal2/mouth_c3","x":0.62,"y":-40.11,"rotation":-89.91,"width":23,"height":32},"mouth_d1":{"name":"normal2/mouth_d1","x":-1.19,"y":-34.96,"rotation":-90,"width":58,"height":33},"mouth_d2":{"name":"normal2/mouth_d2","x":0.01,"y":-33.75,"rotation":-90,"width":56,"height":28},"mouth_d3":{"name":"normal2/mouth_d3","x":-1.8,"y":-32.54,"rotation":270,"width":69,"height":31},"mouth_d4":{"name":"normal2/mouth_d4","x":-2.1,"y":-33.15,"rotation":-90,"width":56,"height":28},"mouth_d5":{"name":"normal2/mouth_d5","x":-0.59,"y":-34.96,"rotation":-90,"width":51,"height":32},"mouth_d6":{"name":"normal2/mouth_d6","x":-0.28,"y":-33.75,"rotation":-90,"width":42,"height":31},"mouth_d7":{"name":"normal2/mouth_d7","x":-1.19,"y":-32.54,"rotation":-90,"width":53,"height":30},"mouth_d8":{"name":"normal2/mouth_d8","x":-1.8,"y":-32.24,"rotation":-90,"width":65,"height":31},"mouth_d9":{"name":"normal2/mouth_d9","x":-1.19,"y":-37.08,"rotation":-90,"width":38,"height":44}},"particle1":{"particle1":{"name":"normal2/particle","x":188.66,"y":-8.63,"rotation":-90,"width":104,"height":104}},"particle10":{"particle10":{"name":"normal2/particle","x":75.28,"y":-92.04,"rotation":-90,"width":104,"height":104}},"particle12":{"particle12":{"name":"normal2/particle","x":155,"width":104,"height":104}},"particle13":{"particle13":{"name":"normal2/particle","x":285.5,"y":689.2,"width":104,"height":104}},"particle14":{"particle14":{"name":"normal2/particle","x":175.2,"y":551,"width":104,"height":104}},"particle15":{"particle15":{"name":"normal2/particle","x":29.88,"y":662.2,"width":104,"height":104}},"particle16":{"particle16":{"name":"normal2/particle","x":119.71,"y":-19.97,"rotation":-90,"width":104,"height":104}},"particle2":{"particle2":{"name":"normal2/particle","x":14.93,"y":-2.91,"rotation":75.29,"width":104,"height":104}},"particle3":{"particle3":{"name":"normal2/particle","x":2.14,"y":36.89,"rotation":-90,"width":104,"height":104}},"particle4":{"particle4":{"name":"normal2/particle","x":13.37,"y":-4.16,"rotation":47.66,"width":104,"height":104}},"particle5":{"particle5":{"name":"normal2/particle","x":-1.23,"y":7.54,"rotation":90.24,"width":104,"height":104}},"particle6":{"particle6":{"name":"normal2/particle","x":3.86,"y":-0.19,"rotation":89.74,"width":104,"height":104}},"particle7":{"particle7":{"name":"normal2/particle","x":-19.62,"y":-1.86,"width":104,"height":104}},"particle8":{"particle8":{"name":"normal2/particle","x":40.01,"y":-1.62,"rotation":-90,"width":104,"height":104}},"particle9":{"particle9":{"name":"normal2/particle","x":76.09,"y":105.55,"rotation":-90,"width":104,"height":104}},"ponytail3":{"ponytail":{"name":"normal2/ponytail3","x":52.88,"y":-8.13,"rotation":90,"width":94,"height":116}},"shin1":{"shin1_a":{"name":"normal2/shin1_a","x":20.57,"y":4.44,"rotation":90,"width":62,"height":41},"shin1_i":{"name":"normal2/shin1_a","x":20.57,"y":4.44,"rotation":90,"width":62,"height":41},"shin1_b":{"name":"normal2/shin1_b","x":13.16,"y":6.51,"rotation":10.32,"width":50,"height":57}},"shin2":{"shin2":{"name":"normal2/shin2_a","x":17.98,"y":0.5,"rotation":90,"width":55,"height":37},"shin2_i":{"name":"normal2/shin2_a","x":17.98,"y":0.5,"rotation":90,"width":55,"height":37}},"torso1":{"torso1":{"name":"normal2/torso1","x":79.78,"y":-3.31,"rotation":-90,"width":105,"height":105}},"torso2_back":{"torso2":{"name":"normal2/torso2","x":38.47,"y":0.76,"rotation":-90,"width":113,"height":98}}}},"events":{"PLAY:tournamentFireBurn1":{},"PLAY:tournamentFootStep2":{},"PLAY:tournamentHitGround2":{},"PLAY:tournamentIceDamage1":{},"PLAY:tournamentJumpGround1":{},"PLAY:tournamentLandGround1":{},"PLAY:tournamentRockWoosh3":{},"PLAY:tournamentRocksLift2":{},"PLAY:tournamentScifiBeep2":{},"PLAY:tournamentScifiBeep3":{},"PLAY:tournamentScifiBeep4":{},"PLAY:tournamentScifiBeep5":{},"PLAY:tournamentScifiInterface3":{},"PLAY:tournamentScifiInterface4":{},"PLAY:tournamentScifiInterface5":{},"PLAY:tournamentScifiTeleport1":{},"PLAY:tournamentSwoosh5":{},"PLAY:tournamentWindDamage1":{},"PLAY:tournamentWindDamage2":{"string":"windDamage1/windDamage1.json"},"SPAWN:particle10:anxiousDrops1":{},"SPAWN:particle12:normalChargeEarth49":{},"SPAWN:particle12:normalChargeEarth50":{"string":"normalChargeEarth16/normalChargeEarth49.json"},"SPAWN:particle16:scifiTeleport1":{},"SPAWN:particle16:scifiTeleport2":{"string":"scifiTeleport1/scifiTeleport1.json"},"SPAWN:particle16:scifiTeleport3":{"string":"scifiTeleport1/scifiTeleport1.json"},"SPAWN:particle16:scifiTeleport4":{},"SPAWN:particle16:scifiTeleport5":{"string":"scifiTeleport2/scifiTeleport4.json"},"SPAWN:particle16:scifiTeleport6":{"string":"scifiTeleport2/scifiTeleport4.json"},"SPAWN:particle1:superHit1":{},"SPAWN:particle1:superHit2":{"string":"superHit1/superHit1.json"},"SPAWN:particle6:dustFloor1":{},"SPAWN:particle6:dustFloor2":{"string":"dustFloor1/dustFloor1.json"},"SPAWN:particle8:fireAshes1":{},"SPAWN:particle8:fireDamage1":{},"SPAWN:particle8:fireDamage2":{"string":"fireDamage1/fireDamage1.json"},"SPAWN:particle9:anxiousDrops2":{"string":"anxiousDrops1/anxiousDrops1.json"},"STAGESPAWN:self:-150:0:front:dustFloor1":{},"STAGESPAWN:self:-150:0:front:dustFloor2":{"string":"dustFloor1/dustFloor1.json"},"STAGESPAWN:self:-50:-120:front:iceDamage1":{},"STAGESPAWN:self:-50:-120:front:iceDamage2":{"string":"iceDamage1/iceDamage1.json"},"STAGESPAWN:self:0:-300:back:thinkImpatient2":{},"STAGESPAWN:self:0:0:back:landingHalo1":{},"STAGESPAWN:self:0:0:front:dustFloor1":{},"STAGESPAWN:self:0:0:front:dustFloor2":{"string":"dustFloor1/dustFloor1.json"},"STAGESPAWN:self:0:0:front:landingSmoke1":{"string":"landingSmoke1/landingHalo1.json"},"STAGESPAWN:self:0:0:front:landingSmoke2":{"string":"landingSmoke1/landingSmoke1.json"},"STAGESPAWN:self:0:0:front:landingSmoke3":{"string":"landingSmoke1/landingSmoke1.json"},"STAGESPAWN:self:0:0:front:windDamage1":{},"STAGESPAWN:self:0:0:front:windDamage2":{"string":"windDamage1/windDamage1.json"},"STAGESPAWN:self:0:0:front:windDamage3":{"string":"windDamage1/windDamage1.json"},"STAGESPAWN:self:0:0:front:windDamage4":{"string":"windDamage1/windDamage1.json"},"STAGESPAWN:self:30:0:front:dustFloor1":{}},"animations":{"appear_alpha":{"slots":{"antenna":{"color":[{"time":0,"color":"ffffffff","curve":"stepped"},{"time":1.1333,"color":"ffffffff"}],"attachment":[{"time":0,"name":null},{"time":0.4666,"name":"antenna"},{"time":1.1333,"name":"antenna"}]},"appear_blue":{"color":[{"time":0,"color":"ffffffff","curve":"stepped"},{"time":1.1333,"color":"ffffffff"}],"attachment":[{"time":0,"name":null},{"time":1.1333,"name":null}]},"appear_mag":{"color":[{"time":0,"color":"ffffffff","curve":"stepped"},{"time":1.1333,"color":"ffffffff"}],"attachment":[{"time":0,"name":null},{"time":0.2,"name":"1"},{"time":0.2666,"name":"2"},{"time":0.3333,"name":"3"},{"time":0.4,"name":"4"},{"time":0.4666,"name":"5"},{"time":0.5333,"name":"6"},{"time":0.6,"name":"7"},{"time":0.6666,"name":"8"},{"time":0.7333,"name":"9"},{"time":0.8,"name":"10"},{"time":0.8666,"name":"11"},{"time":0.9333,"name":null},{"time":1.1333,"name":null}]},"arm1":{"color":[{"time":0,"color":"ffffffff","curve":"stepped"},{"time":1.1333,"color":"ffffffff"}],"attachment":[{"time":0,"name":null},{"time":0.4666,"name":"arm1_a"},{"time":1.1333,"name":"arm1_a"}]},"arm2":{"color":[{"time":0,"color":"ffffffff","curve":"stepped"},{"time":1.1333,"color":"ffffffff"}],"attachment":[{"time":0,"name":null},{"time":0.4666,"name":"arm2"},{"time":1.1333,"name":"arm2"}]},"cheer_flag":{"color":[{"time":0,"color":"ffffffff","curve":"stepped"},{"time":1.1333,"color":"ffffffff"}],"attachment":[{"time":0,"name":null},{"time":1.1333,"name":null}]},"cheer_glove":{"color":[{"time":0,"color":"ffffffff","curve":"stepped"},{"time":1.1333,"color":"ffffffff"}],"attachment":[{"time":0,"name":null},{"time":1.1333,"name":null}]},"eyes":{"color":[{"time":0,"color":"ffffffff","curve":"stepped"},{"time":1.1333,"color":"ffffffff"}],"attachment":[{"time":0,"name":null},{"time":0.4666,"name":"eyes_d2"},{"time":0.9333,"name":"eyes_a1"},{"time":1.1333,"name":"eyes_a1"}]},"faceshield":{"color":[{"time":0,"color":"ffffffff","curve":"stepped"},{"time":1.1333,"color":"ffffffff"}],"attachment":[{"time":0,"name":null},{"time":0.4666,"name":"faceshield"},{"time":1.1333,"name":"faceshield"}]},"foot1":{"color":[{"time":0,"color":"ffffffff","curve":"stepped"},{"time":1.1333,"color":"ffffffff"}],"attachment":[{"time":0,"name":null},{"time":0.4666,"name":"foot1_d"},{"time":1.1333,"name":"foot1_d"}]},"foot2":{"color":[{"time":0,"color":"ffffffff","curve":"stepped"},{"time":1.1333,"color":"ffffffff"}],"attachment":[{"time":0,"name":null},{"time":0.4666,"name":"foot2_a"},{"time":1.1333,"name":"foot2_a"}]},"forearm1":{"color":[{"time":0,"color":"ffffffff","curve":"stepped"},{"time":1.1333,"color":"ffffffff"}],"attachment":[{"time":0,"name":null},{"time":0.4666,"name":"forearm1_a"},{"time":1.1333,"name":"forearm1_a"}]},"forearm2":{"color":[{"time":0,"color":"ffffffff","curve":"stepped"},{"time":1.1333,"color":"ffffffff"}],"attachment":[{"time":0,"name":null},{"time":0.4666,"name":"forearm2_a"},{"time":1.1333,"name":"forearm2_a"}]},"hand1":{"color":[{"time":0,"color":"ffffffff","curve":"stepped"},{"time":1.1333,"color":"ffffffff"}],"attachment":[{"time":0,"name":null},{"time":0.4666,"name":"hand1_a"},{"time":1.1333,"name":"hand1_a"}]},"hand2":{"color":[{"time":0,"color":"ffffffff","curve":"stepped"},{"time":1.1333,"color":"ffffffff"}],"attachment":[{"time":0,"name":null},{"time":0.4666,"name":"hand2_a"},{"time":1.1333,"name":"hand2_h"}]},"head":{"color":[{"time":0,"color":"ffffffff","curve":"stepped"},{"time":1.1333,"color":"ffffffff"}],"attachment":[{"time":0,"name":null},{"time":0.4666,"name":"head"},{"time":1.1333,"name":"head"}]},"leg1":{"color":[{"time":0,"color":"ffffffff","curve":"stepped"},{"time":1.1333,"color":"ffffffff"}],"attachment":[{"time":0,"name":null},{"time":0.4666,"name":"leg1_a"},{"time":1.1333,"name":"leg1_a"}]},"leg2":{"color":[{"time":0,"color":"ffffffff","curve":"stepped"},{"time":1.1333,"color":"ffffffff"}],"attachment":[{"time":0,"name":null},{"time":0.4666,"name":"leg2_a"},{"time":1.1333,"name":"leg2_a"}]},"mouth":{"color":[{"time":0,"color":"ffffffff","curve":"stepped"},{"time":1.1333,"color":"ffffffff"}],"attachment":[{"time":0,"name":null},{"time":0.4666,"name":"mouth_a1"},{"time":0.6,"name":"mouth_a1"},{"time":0.7,"name":"mouth_b1"},{"time":0.9666,"name":"mouth_b1"},{"time":1.1333,"name":"mouth_b1"}]},"particle1":{"color":[{"time":0,"color":"ffffffff","curve":"stepped"},{"time":1.1333,"color":"ffffffff"}],"attachment":[{"time":0,"name":null},{"time":0.4666,"name":"particle1"},{"time":1.1333,"name":"particle1"}]},"ponytail3":{"color":[{"time":0,"color":"ffffffff","curve":"stepped"},{"time":1.1333,"color":"ffffffff"}],"attachment":[{"time":0,"name":null},{"time":0.4666,"name":"ponytail"},{"time":1.1333,"name":"ponytail"}]},"shin1":{"color":[{"time":0,"color":"ffffffff","curve":"stepped"},{"time":1.1333,"color":"ffffffff"}],"attachment":[{"time":0,"name":null},{"time":0.4666,"name":"shin1_a"},{"time":1.1333,"name":"shin1_a"}]},"shin2":{"color":[{"time":0,"color":"ffffffff","curve":"stepped"},{"time":1.1333,"color":"ffffffff"}],"attachment":[{"time":0,"name":null},{"time":0.4666,"name":"shin2"},{"time":1.1333,"name":"shin2"}]},"torso1":{"color":[{"time":0,"color":"ffffffff","curve":"stepped"},{"time":1.1333,"color":"ffffffff"}],"attachment":[{"time":0,"name":null},{"time":0.4666,"name":"torso1"},{"time":1.1333,"name":"torso1"}]},"torso2":{"color":[{"time":0,"color":"ffffffff","curve":"stepped"},{"time":1.1333,"color":"ffffffff"}],"attachment":[{"time":0,"name":null},{"time":0.4666,"name":"torso2"},{"time":1.1333,"name":"torso2"}]},"torso2_back":{"color":[{"time":0,"color":"ffffffff","curve":"stepped"},{"time":1.1333,"color":"ffffffff"}],"attachment":[{"time":0,"name":null},{"time":0.4666,"name":"torso2"},{"time":1.1333,"name":"torso2"}]}},"bones":{"hand1":{"rotate":[{"time":0,"angle":0,"curve":"stepped"},{"time":0.4666,"angle":6.13,"curve":[0.42,-0.82,0.568,1]},{"time":1.1333,"angle":0}],"translate":[{"time":0,"x":-4.23,"y":0}],"scale":[{"time":0,"x":1,"y":1}]},"influence_bone":{"rotate":[{"time":0,"angle":0}],"translate":[{"time":0,"x":0,"y":0}],"scale":[{"time":0,"x":1,"y":1}]},"foot2":{"rotate":[{"time":0,"angle":-8.75,"curve":"stepped"},{"time":0.4666,"angle":-360.63,"curve":[0.42,-0.82,0.568,1]},{"time":1.1333,"angle":-8.75}],"translate":[{"time":0,"x":2.88,"y":-1.89,"curve":"stepped"},{"time":0.4666,"x":1.31,"y":-1.89,"curve":[0.42,-0.82,0.568,1]},{"time":1.1333,"x":2.88,"y":-1.89}],"scale":[{"time":0,"x":1,"y":1}]},"hand2":{"rotate":[{"time":0,"angle":5.06,"curve":"stepped"},{"time":0.4666,"angle":22.57,"curve":[0.42,-0.82,0.568,1]},{"time":1.1333,"angle":5.06}],"translate":[{"time":0,"x":0,"y":0,"curve":"stepped"},{"time":0.4666,"x":0.38,"y":-5.22,"curve":[0.25,0,0.75,1]},{"time":1.1333,"x":0,"y":0}],"scale":[{"time":0,"x":1,"y":1}]},"clavicle1":{"rotate":[{"time":0,"angle":0,"curve":"stepped"},{"time":0.4666,"angle":0,"curve":"stepped"},{"time":1.1333,"angle":0}],"translate":[{"time":0,"x":0,"y":0,"curve":"stepped"},{"time":0.4666,"x":-6.42,"y":-7.72,"curve":[0.42,-0.82,0.568,1]},{"time":1.1333,"x":0,"y":0}],"scale":[{"time":0,"x":1,"y":1,"curve":"stepped"},{"time":1.1333,"x":1,"y":1}]},"cog":{"rotate":[{"time":0,"angle":0,"curve":"stepped"},{"time":1.1333,"angle":0}],"translate":[{"time":0,"x":20.52,"y":2.3,"curve":"stepped"},{"time":1.1333,"x":20.52,"y":2.3}],"scale":[{"time":0,"x":1,"y":1,"curve":"stepped"},{"time":1.1333,"x":1,"y":1}]},"leg1":{"rotate":[{"time":0,"angle":-28.73,"curve":"stepped"},{"time":0.4666,"angle":10.02,"curve":[0.42,-0.82,0.568,1]},{"time":1.1333,"angle":-19.96}],"translate":[{"time":0,"x":9.85,"y":9.23,"curve":"stepped"},{"time":0.4666,"x":13.75,"y":7.26,"curve":[0.42,-0.82,0.568,1]},{"time":1.1333,"x":11.44,"y":13.19}],"scale":[{"time":0,"x":1,"y":1}]},"head":{"rotate":[{"time":0,"angle":0.49,"curve":"stepped"},{"time":0.4666,"angle":-3.46,"curve":[0.25,0,0.309,1]},{"time":0.7666,"angle":-15.09,"curve":[0.681,0,0.66,1]},{"time":1.1333,"angle":0.49}],"translate":[{"time":0,"x":0,"y":0,"curve":"stepped"},{"time":0.4666,"x":-15.88,"y":-24.37,"curve":[0.42,-0.82,0.568,1]},{"time":1.1333,"x":0,"y":0}],"scale":[{"time":0,"x":1,"y":1}]},"foot1":{"rotate":[{"time":0,"angle":28.5,"curve":"stepped"},{"time":0.4666,"angle":32.5,"curve":[0.42,-0.82,0.568,1]},{"time":0.8666,"angle":3.4}],"translate":[{"time":0,"x":5.35,"y":10.18,"curve":"stepped"},{"time":0.4666,"x":3.57,"y":11.1,"curve":[0.42,-0.82,0.568,1]},{"time":0.8666,"x":5.46,"y":1.42}],"scale":[{"time":0,"x":1,"y":1}]},"arm2":{"rotate":[{"time":0,"angle":20.99,"curve":"stepped"},{"time":0.4666,"angle":26.52,"curve":[0.42,-0.82,0.568,1]},{"time":1.1333,"angle":20.99}],"translate":[{"time":0,"x":-6.63,"y":5.67}],"scale":[{"time":0,"x":1,"y":1}]},"forearm2":{"rotate":[{"time":0,"angle":72.29,"curve":"stepped"},{"time":0.4666,"angle":92.93,"curve":[0.42,-0.82,0.568,1]},{"time":1.1333,"angle":72.29}],"translate":[{"time":0,"x":0,"y":0}],"scale":[{"time":0,"x":1,"y":1}]},"shin1":{"rotate":[{"time":0,"angle":-35.15,"curve":"stepped"},{"time":0.4666,"angle":-432.05,"curve":[0.42,-0.82,0.568,1]},{"time":1.1333,"angle":-368.77}],"translate":[{"time":0,"x":-2.11,"y":4.65,"curve":"stepped"},{"time":0.4666,"x":-8.68,"y":8.12,"curve":[0.25,0,0.75,1]},{"time":1.1333,"x":-0.18,"y":2.02}],"scale":[{"time":0,"x":1,"y":1}]},"forearm1":{"rotate":[{"time":0,"angle":42.46,"curve":"stepped"},{"time":0.4666,"angle":80.26,"curve":[0.42,-0.82,0.568,1]},{"time":1.1333,"angle":43.92}],"translate":[{"time":0,"x":0,"y":0}],"scale":[{"time":0,"x":1,"y":1}]},"shin2":{"rotate":[{"time":0,"angle":-34.53,"curve":"stepped"},{"time":0.4666,"angle":-405.16,"curve":[0.42,-0.82,0.568,1]},{"time":1.1333,"angle":-383.57}],"translate":[{"time":0,"x":-3.83,"y":1.47,"curve":"stepped"},{"time":0.4666,"x":-7.7,"y":6.67,"curve":[0.42,-0.82,0.568,1]},{"time":1.1333,"x":-3.83,"y":1.47}],"scale":[{"time":0,"x":1,"y":1}]},"particles_foot_bone":{"rotate":[{"time":0,"angle":0}],"translate":[{"time":0,"x":0,"y":0}],"scale":[{"time":0,"x":1,"y":1}]},"clavicle2":{"rotate":[{"time":0,"angle":0,"curve":"stepped"},{"time":1.1333,"angle":0}],"translate":[{"time":0,"x":0,"y":0,"curve":"stepped"},{"time":0.4666,"x":-4.58,"y":7.14,"curve":[0.42,-0.82,0.568,1]},{"time":1.1333,"x":0,"y":0}],"scale":[{"time":0,"x":1,"y":1,"curve":"stepped"},{"time":1.1333,"x":1,"y":1}]},"body":{"rotate":[{"time":0,"angle":0,"curve":"stepped"},{"time":1.1333,"angle":0}],"translate":[{"time":0,"x":0,"y":-3.63,"curve":"stepped"},{"time":1.1333,"x":0,"y":-3.63}],"scale":[{"time":0,"x":1,"y":1,"curve":"stepped"},{"time":1.1333,"x":1,"y":1}]},"torso":{"rotate":[{"time":0,"angle":-7.26,"curve":"stepped"},{"time":0.4666,"angle":-10.49,"curve":[0.25,0,0.75,1]},{"time":1.1333,"angle":-2.21}],"translate":[{"time":0,"x":4.31,"y":3.07,"curve":"stepped"},{"time":0.4666,"x":-0.85,"y":-11.98,"curve":[0.42,-0.82,0.568,1]},{"time":1.1333,"x":1.14,"y":7.04}],"scale":[{"time":0,"x":1,"y":1,"curve":"stepped"},{"time":0.4666,"x":0.972,"y":1,"curve":[0.42,-0.82,0.568,1]},{"time":1.1333,"x":1,"y":1}]},"root":{"rotate":[{"time":0,"angle":0}],"translate":[{"time":0,"x":0,"y":0}],"scale":[{"time":0,"x":1,"y":1}]},"antenna":{"rotate":[{"time":0,"angle":0,"curve":"stepped"},{"time":0.4666,"angle":-3.38,"curve":[0.42,-0.82,0.568,1]},{"time":1.1333,"angle":0}],"translate":[{"time":0,"x":0,"y":0}],"scale":[{"time":0,"x":1,"y":1}]},"tail":{"rotate":[{"time":0,"angle":0,"curve":[0.25,0,0.75,1]},{"time":0.4666,"angle":-350.34,"curve":[0.762,0,0.864,0.86]},{"time":0.7333,"angle":-22.28,"curve":[0.46,-0.71,0.624,1.65]},{"time":1.1333,"angle":0}],"translate":[{"time":0,"x":0,"y":0}],"scale":[{"time":0,"x":1,"y":1}]},"leg2":{"rotate":[{"time":0,"angle":44.98,"curve":"stepped"},{"time":0.4666,"angle":45.14,"curve":[0.42,-0.82,0.568,1]},{"time":1.1333,"angle":35.47}],"translate":[{"time":0,"x":0,"y":0,"curve":"stepped"},{"time":0.4666,"x":3.57,"y":-7.66,"curve":[0.42,-0.82,0.568,1]},{"time":1.1333,"x":0,"y":3.96}],"scale":[{"time":0,"x":1,"y":1}]},"arm1":{"rotate":[{"time":0,"angle":-55.8,"curve":"stepped"},{"time":0.4666,"angle":34.48,"curve":[0.42,-0.82,0.568,1]},{"time":1.1333,"angle":-13.6}],"translate":[{"time":0,"x":-8.89,"y":-2.18}],"scale":[{"time":0,"x":1,"y":1}]}},"drawOrder":[{"time":0,"offsets":[{"slot":"hand1","offset":5},{"slot":"forearm1","offset":5}]},{"time":1.1333,"offsets":[{"slot":"hand1","offset":5},{"slot":"forearm1","offset":5}]}],"events":[{"time":0.3,"name":"PLAY:tournamentScifiTeleport1"},{"time":0.3333,"name":"SPAWN:particle16:scifiTeleport4","string":"scifiTeleport2/scifiTeleport4.json"},{"time":0.3333,"name":"SPAWN:particle16:scifiTeleport5","string":"scifiTeleport2/scifiTeleport5.json"},{"time":0.3333,"name":"SPAWN:particle16:scifiTeleport6","string":"scifiTeleport2/scifiTeleport6.json"},{"time":0.5666,"name":"PLAY:tournamentLandGround1"},{"time":0.5666,"name":"STAGESPAWN:self:0:0:back:landingHalo1","string":"landingSmoke1/landingHalo1.json"},{"time":0.5666,"name":"STAGESPAWN:self:0:0:front:landingSmoke1","string":"landingSmoke1/landingSmoke1.json"},{"time":0.5666,"name":"STAGESPAWN:self:0:0:front:landingSmoke2","string":"landingSmoke1/landingSmoke2.json"},{"time":0.5666,"name":"STAGESPAWN:self:0:0:front:landingSmoke3","string":"landingSmoke1/landingSmoke3.json"}]},"appear_delta":{"slots":{"antenna":{"color":[{"time":0,"color":"ffffffff","curve":"stepped"},{"time":1.1333,"color":"ffffffff"}],"attachment":[{"time":0,"name":null},{"time":0.4,"name":"antenna"},{"time":1.1333,"name":"antenna"}]},"appear_blue":{"color":[{"time":0,"color":"ffffffff","curve":"stepped"},{"time":1.1333,"color":"ffffffff"}],"attachment":[{"time":0,"name":"1"},{"time":0.2,"name":"2"},{"time":0.2666,"name":"3"},{"time":0.3333,"name":"3_2"},{"time":0.4,"name":"4"},{"time":0.4666,"name":"6"},{"time":0.5333,"name":"7"},{"time":0.6,"name":"8"},{"time":0.6666,"name":"9"},{"time":0.7333,"name":"10"},{"time":0.8,"name":"11"},{"time":0.8666,"name":null},{"time":1.1333,"name":null}]},"appear_mag":{"color":[{"time":0,"color":"ffffffff","curve":"stepped"},{"time":1.1333,"color":"ffffffff"}],"attachment":[{"time":0,"name":null},{"time":1.1333,"name":null}]},"arm1":{"color":[{"time":0,"color":"ffffffff","curve":"stepped"},{"time":1.1333,"color":"ffffffff"}],"attachment":[{"time":0,"name":null},{"time":0.3666,"name":"arm1_a"},{"time":1.1333,"name":"arm1_a"}]},"arm2":{"color":[{"time":0,"color":"ffffffff","curve":"stepped"},{"time":1.1333,"color":"ffffffff"}],"attachment":[{"time":0,"name":null},{"time":0.4,"name":"arm2"},{"time":1.1333,"name":"arm2"}]},"cheer_flag":{"color":[{"time":0,"color":"ffffffff","curve":"stepped"},{"time":1.1333,"color":"ffffffff"}],"attachment":[{"time":0,"name":null},{"time":1.1333,"name":null}]},"cheer_glove":{"color":[{"time":0,"color":"ffffffff","curve":"stepped"},{"time":1.1333,"color":"ffffffff"}],"attachment":[{"time":0,"name":null},{"time":1.1333,"name":null}]},"eyes":{"color":[{"time":0,"color":"ffffffff","curve":"stepped"},{"time":1.1333,"color":"ffffffff"}],"attachment":[{"time":0,"name":null},{"time":0.4,"name":"eyes_d2"},{"time":0.9333,"name":"eyes_a1"},{"time":1.1333,"name":"eyes_a1"}]},"faceshield":{"color":[{"time":0,"color":"ffffffff","curve":"stepped"},{"time":1.1333,"color":"ffffffff"}],"attachment":[{"time":0,"name":null},{"time":0.4,"name":"faceshield"},{"time":1.1333,"name":"faceshield"}]},"foot1":{"color":[{"time":0,"color":"ffffffff","curve":"stepped"},{"time":1.1333,"color":"ffffffff"}],"attachment":[{"time":0,"name":null},{"time":0.4,"name":"foot1_d"},{"time":1.1333,"name":"foot1_d"}]},"foot2":{"color":[{"time":0,"color":"ffffffff","curve":"stepped"},{"time":1.1333,"color":"ffffffff"}],"attachment":[{"time":0,"name":null},{"time":0.4,"name":"foot2_a"},{"time":1.1333,"name":"foot2_a"}]},"forearm1":{"color":[{"time":0,"color":"ffffffff","curve":"stepped"},{"time":1.1333,"color":"ffffffff"}],"attachment":[{"time":0,"name":null},{"time":0.4,"name":"forearm1_a"},{"time":1.1333,"name":"forearm1_a"}]},"forearm2":{"color":[{"time":0,"color":"ffffffff","curve":"stepped"},{"time":1.1333,"color":"ffffffff"}],"attachment":[{"time":0,"name":null},{"time":0.4,"name":"forearm2_a"},{"time":1.1333,"name":"forearm2_a"}]},"hand1":{"color":[{"time":0,"color":"ffffffff","curve":"stepped"},{"time":1.1333,"color":"ffffffff"}],"attachment":[{"time":0,"name":null},{"time":0.3666,"name":"hand1_a"},{"time":1.1333,"name":"hand1_a"}]},"hand2":{"color":[{"time":0,"color":"ffffffff","curve":"stepped"},{"time":1.1333,"color":"ffffffff"}],"attachment":[{"time":0,"name":null},{"time":0.3666,"name":"hand2_a"},{"time":1.1333,"name":"hand2_h"}]},"head":{"color":[{"time":0,"color":"ffffffff","curve":"stepped"},{"time":1.1333,"color":"ffffffff"}],"attachment":[{"time":0,"name":null},{"time":0.4,"name":"head"},{"time":1.1333,"name":"head"}]},"leg1":{"color":[{"time":0,"color":"ffffffff","curve":"stepped"},{"time":1.1333,"color":"ffffffff"}],"attachment":[{"time":0,"name":null},{"time":0.4,"name":"leg1_a"},{"time":1.1333,"name":"leg1_a"}]},"leg2":{"color":[{"time":0,"color":"ffffffff","curve":"stepped"},{"time":1.1333,"color":"ffffffff"}],"attachment":[{"time":0,"name":null},{"time":0.4,"name":"leg2_a"},{"time":1.1333,"name":"leg2_a"}]},"mouth":{"color":[{"time":0,"color":"ffffffff","curve":"stepped"},{"time":1.1333,"color":"ffffffff"}],"attachment":[{"time":0,"name":null},{"time":0.4,"name":"mouth_a1"},{"time":0.6,"name":"mouth_a1"},{"time":0.7,"name":"mouth_b1"},{"time":0.9666,"name":"mouth_b1"},{"time":1.1333,"name":"mouth_b1"}]},"particle1":{"color":[{"time":0,"color":"ffffffff","curve":"stepped"},{"time":1.1333,"color":"ffffffff"}],"attachment":[{"time":0,"name":null},{"time":0.4,"name":"particle1"},{"time":1.1333,"name":"particle1"}]},"ponytail3":{"color":[{"time":0,"color":"ffffffff","curve":"stepped"},{"time":1.1333,"color":"ffffffff"}],"attachment":[{"time":0,"name":null},{"time":0.4,"name":"ponytail"},{"time":1.1333,"name":"ponytail"}]},"shin1":{"color":[{"time":0,"color":"ffffffff","curve":"stepped"},{"time":1.1333,"color":"ffffffff"}],"attachment":[{"time":0,"name":null},{"time":0.3666,"name":"shin1_a"},{"time":1.1333,"name":"shin1_a"}]},"shin2":{"color":[{"time":0,"color":"ffffffff","curve":"stepped"},{"time":1.1333,"color":"ffffffff"}],"attachment":[{"time":0,"name":null},{"time":0.4,"name":"shin2"},{"time":1.1333,"name":"shin2"}]},"torso1":{"color":[{"time":0,"color":"ffffffff","curve":"stepped"},{"time":1.1333,"color":"ffffffff"}],"attachment":[{"time":0,"name":null},{"time":0.4,"name":"torso1"},{"time":1.1333,"name":"torso1"}]},"torso2":{"color":[{"time":0,"color":"ffffffff","curve":"stepped"},{"time":1.1333,"color":"ffffffff"}],"attachment":[{"time":0,"name":null},{"time":0.4,"name":"torso2"},{"time":1.1333,"name":"torso2"}]},"torso2_back":{"color":[{"time":0,"color":"ffffffff","curve":"stepped"},{"time":1.1333,"color":"ffffffff"}],"attachment":[{"time":0,"name":null},{"time":0.4,"name":"torso2"},{"time":1.1333,"name":"torso2"}]}},"bones":{"leg1":{"rotate":[{"time":0,"angle":-28.73,"curve":"stepped"},{"time":0.4,"angle":10.02,"curve":[0.42,-0.82,0.568,1]},{"time":1.1333,"angle":-19.96}],"translate":[{"time":0,"x":9.85,"y":9.23,"curve":"stepped"},{"time":0.4,"x":13.75,"y":7.26,"curve":[0.42,-0.82,0.568,1]},{"time":1.1333,"x":11.44,"y":13.19}],"scale":[{"time":0,"x":1,"y":1}]},"shin1":{"rotate":[{"time":0,"angle":-35.15,"curve":"stepped"},{"time":0.4,"angle":-432.05,"curve":[0.42,-0.82,0.568,1]},{"time":1.1333,"angle":-368.77}],"translate":[{"time":0,"x":-2.11,"y":4.65,"curve":"stepped"},{"time":0.4,"x":-8.68,"y":8.12,"curve":[0.25,0,0.75,1]},{"time":1.1333,"x":-0.18,"y":2.02}],"scale":[{"time":0,"x":1,"y":1}]},"foot1":{"rotate":[{"time":0,"angle":28.5,"curve":"stepped"},{"time":0.4,"angle":32.5,"curve":[0.42,-0.82,0.568,1]},{"time":0.8666,"angle":3.4}],"translate":[{"time":0,"x":5.35,"y":10.18,"curve":"stepped"},{"time":0.4,"x":3.57,"y":11.1,"curve":[0.42,-0.82,0.568,1]},{"time":0.8666,"x":5.46,"y":1.42}],"scale":[{"time":0,"x":1,"y":1}]},"arm1":{"rotate":[{"time":0,"angle":-55.8,"curve":"stepped"},{"time":0.4,"angle":34.48,"curve":[0.42,-0.82,0.568,1]},{"time":1.1333,"angle":-13.6}],"translate":[{"time":0,"x":-8.89,"y":-2.18}],"scale":[{"time":0,"x":1,"y":1}]},"forearm1":{"rotate":[{"time":0,"angle":42.46,"curve":"stepped"},{"time":0.4,"angle":80.26,"curve":[0.42,-0.82,0.568,1]},{"time":1.1333,"angle":43.92}],"translate":[{"time":0,"x":0,"y":0}],"scale":[{"time":0,"x":1,"y":1}]},"head":{"rotate":[{"time":0,"angle":0.49,"curve":"stepped"},{"time":0.4,"angle":-3.46,"curve":[0.25,0,0.309,1]},{"time":0.7666,"angle":-15.09,"curve":[0.681,0,0.66,1]},{"time":1.1333,"angle":0.49}],"translate":[{"time":0,"x":0,"y":0,"curve":"stepped"},{"time":0.4,"x":-15.88,"y":-24.37,"curve":[0.42,-0.82,0.568,1]},{"time":1.1333,"x":0,"y":0}],"scale":[{"time":0,"x":1,"y":1}]},"leg2":{"rotate":[{"time":0,"angle":44.98,"curve":"stepped"},{"time":0.4,"angle":45.14,"curve":[0.42,-0.82,0.568,1]},{"time":1.1333,"angle":35.47}],"translate":[{"time":0,"x":0,"y":0,"curve":"stepped"},{"time":0.4,"x":3.57,"y":-7.66,"curve":[0.42,-0.82,0.568,1]},{"time":1.1333,"x":0,"y":3.96}],"scale":[{"time":0,"x":1,"y":1}]},"clavicle2":{"rotate":[{"time":0,"angle":0,"curve":"stepped"},{"time":1.1333,"angle":0}],"translate":[{"time":0,"x":0,"y":0,"curve":"stepped"},{"time":0.4,"x":-4.58,"y":7.14,"curve":[0.42,-0.82,0.568,1]},{"time":1.1333,"x":0,"y":0}],"scale":[{"time":0,"x":1,"y":1,"curve":"stepped"},{"time":1.1333,"x":1,"y":1}]},"influence_bone":{"rotate":[{"time":0,"angle":0}],"translate":[{"time":0,"x":0,"y":0}],"scale":[{"time":0,"x":1,"y":1}]},"root":{"rotate":[{"time":0,"angle":0}],"translate":[{"time":0,"x":0,"y":0}],"scale":[{"time":0,"x":1,"y":1}]},"antenna":{"rotate":[{"time":0,"angle":0,"curve":"stepped"},{"time":0.4,"angle":-3.38,"curve":[0.42,-0.82,0.568,1]},{"time":1.1333,"angle":0}],"translate":[{"time":0,"x":0,"y":0}],"scale":[{"time":0,"x":1,"y":1}]},"body":{"rotate":[{"time":0,"angle":0,"curve":"stepped"},{"time":1.1333,"angle":0}],"translate":[{"time":0,"x":0,"y":-3.63,"curve":"stepped"},{"time":1.1333,"x":0,"y":-3.63}],"scale":[{"time":0,"x":1,"y":1,"curve":"stepped"},{"time":1.1333,"x":1,"y":1}]},"hand1":{"rotate":[{"time":0,"angle":0,"curve":"stepped"},{"time":0.4,"angle":6.13,"curve":[0.42,-0.82,0.568,1]},{"time":1.1333,"angle":0}],"translate":[{"time":0,"x":-4.23,"y":0}],"scale":[{"time":0,"x":1,"y":1}]},"torso":{"rotate":[{"time":0,"angle":-7.26,"curve":"stepped"},{"time":0.4,"angle":-10.49,"curve":[0.25,0,0.75,1]},{"time":1.1333,"angle":-2.21}],"translate":[{"time":0,"x":4.31,"y":3.07,"curve":"stepped"},{"time":0.4,"x":-0.85,"y":-11.98,"curve":[0.42,-0.82,0.568,1]},{"time":1.1333,"x":1.14,"y":7.04}],"scale":[{"time":0,"x":1,"y":1,"curve":"stepped"},{"time":0.4,"x":0.972,"y":1,"curve":[0.42,-0.82,0.568,1]},{"time":1.1333,"x":1,"y":1}]},"shin2":{"rotate":[{"time":0,"angle":-34.53,"curve":"stepped"},{"time":0.4,"angle":-405.16,"curve":[0.42,-0.82,0.568,1]},{"time":1.1333,"angle":-383.57}],"translate":[{"time":0,"x":-3.83,"y":1.47,"curve":"stepped"},{"time":0.4,"x":-7.7,"y":6.67,"curve":[0.42,-0.82,0.568,1]},{"time":1.1333,"x":-3.83,"y":1.47}],"scale":[{"time":0,"x":1,"y":1}]},"foot2":{"rotate":[{"time":0,"angle":-8.75,"curve":"stepped"},{"time":0.4,"angle":-360.63,"curve":[0.42,-0.82,0.568,1]},{"time":1.1333,"angle":-8.75}],"translate":[{"time":0,"x":2.88,"y":-1.89,"curve":"stepped"},{"time":0.4,"x":1.31,"y":-1.89,"curve":[0.42,-0.82,0.568,1]},{"time":1.1333,"x":2.88,"y":-1.89}],"scale":[{"time":0,"x":1,"y":1}]},"cog":{"rotate":[{"time":0,"angle":0}],"translate":[{"time":0,"x":20.52,"y":2.3}],"scale":[{"time":0,"x":1,"y":1}]},"arm2":{"rotate":[{"time":0,"angle":20.99,"curve":"stepped"},{"time":0.4,"angle":26.52,"curve":[0.42,-0.82,0.568,1]},{"time":1.1333,"angle":20.99}],"translate":[{"time":0,"x":-6.63,"y":5.67}],"scale":[{"time":0,"x":1,"y":1}]},"particles_foot_bone":{"rotate":[{"time":0,"angle":0}],"translate":[{"time":0,"x":0,"y":0}],"scale":[{"time":0,"x":1,"y":1}]},"hand2":{"rotate":[{"time":0,"angle":5.06,"curve":"stepped"},{"time":0.4,"angle":22.57,"curve":[0.42,-0.82,0.568,1]},{"time":1.1333,"angle":5.06}],"translate":[{"time":0,"x":0,"y":0,"curve":"stepped"},{"time":0.4,"x":0.38,"y":-5.22,"curve":[0.25,0,0.75,1]},{"time":1.1333,"x":0,"y":0}],"scale":[{"time":0,"x":1,"y":1}]},"forearm2":{"rotate":[{"time":0,"angle":72.29,"curve":"stepped"},{"time":0.4,"angle":92.93,"curve":[0.42,-0.82,0.568,1]},{"time":1.1333,"angle":72.29}],"translate":[{"time":0,"x":0,"y":0}],"scale":[{"time":0,"x":1,"y":1}]},"clavicle1":{"rotate":[{"time":0,"angle":0}],"translate":[{"time":0,"x":0,"y":0,"curve":"stepped"},{"time":0.4,"x":-6.42,"y":-7.72,"curve":[0.42,-0.82,0.568,1]},{"time":1.1333,"x":0,"y":0}],"scale":[{"time":0,"x":1,"y":1}]},"tail":{"rotate":[{"time":0,"angle":0,"curve":[0.25,0,0.75,1]},{"time":0.4,"angle":-350.34,"curve":[0.762,0,0.864,0.86]},{"time":0.7333,"angle":-22.28,"curve":[0.46,-0.71,0.624,1.65]},{"time":1.1333,"angle":0}],"translate":[{"time":0,"x":0,"y":0}],"scale":[{"time":0,"x":1,"y":1}]}},"drawOrder":[{"time":0,"offsets":[{"slot":"hand1","offset":5},{"slot":"forearm1","offset":5}]},{"time":1.1333,"offsets":[{"slot":"hand1","offset":5},{"slot":"forearm1","offset":5}]}],"events":[{"time":0.2333,"name":"PLAY:tournamentScifiTeleport1"},{"time":0.2666,"name":"SPAWN:particle16:scifiTeleport1","string":"scifiTeleport1/scifiTeleport1.json"},{"time":0.2666,"name":"SPAWN:particle16:scifiTeleport2","string":"scifiTeleport1/scifiTeleport2.json"},{"time":0.2666,"name":"SPAWN:particle16:scifiTeleport3","string":"scifiTeleport1/scifiTeleport3.json"},{"time":0.6,"name":"PLAY:tournamentLandGround1"},{"time":0.6,"name":"STAGESPAWN:self:0:0:back:landingHalo1","string":"landingSmoke1/landingHalo1.json"},{"time":0.6,"name":"STAGESPAWN:self:0:0:front:landingSmoke1","string":"landingSmoke1/landingSmoke1.json"},{"time":0.6,"name":"STAGESPAWN:self:0:0:front:landingSmoke2","string":"landingSmoke1/landingSmoke2.json"},{"time":0.6,"name":"STAGESPAWN:self:0:0:front:landingSmoke3","string":"landingSmoke1/landingSmoke3.json"}]},"gg":{"slots":{"antenna":{"color":[{"time":0,"color":"ffffffff","curve":"stepped"},{"time":2,"color":"ffffffff"}],"attachment":[{"time":0,"name":"antenna"},{"time":2,"name":"antenna"}]},"appear_blue":{"color":[{"time":0,"color":"ffffffff","curve":"stepped"},{"time":2,"color":"ffffffff"}],"attachment":[{"time":0,"name":null},{"time":2,"name":null}]},"appear_mag":{"color":[{"time":0,"color":"ffffffff","curve":"stepped"},{"time":2,"color":"ffffffff"}],"attachment":[{"time":0,"name":null},{"time":2,"name":null}]},"arm1":{"color":[{"time":0,"color":"ffffffff","curve":"stepped"},{"time":2,"color":"ffffffff"}],"attachment":[{"time":0,"name":"arm1_a"},{"time":2,"name":"arm1_a"}]},"arm2":{"color":[{"time":0,"color":"ffffffff","curve":"stepped"},{"time":2,"color":"ffffffff"}],"attachment":[{"time":0,"name":"arm2"},{"time":2,"name":"arm2"}]},"cheer_flag":{"color":[{"time":0,"color":"ffffffff","curve":"stepped"},{"time":2,"color":"ffffffff"}],"attachment":[{"time":0,"name":null},{"time":2,"name":null}]},"cheer_glove":{"color":[{"time":0,"color":"ffffffff","curve":"stepped"},{"time":2,"color":"ffffffff"}],"attachment":[{"time":0,"name":null},{"time":2,"name":null}]},"eyes":{"color":[{"time":0,"color":"ffffffff","curve":"stepped"},{"time":2,"color":"ffffffff"}],"attachment":[{"time":0,"name":"eyes_g1"},{"time":0.3333,"name":"eyes_h3"},{"time":0.5,"name":"eyes_g1"},{"time":2,"name":"eyes_g1"}]},"faceshield":{"color":[{"time":0,"color":"ffffffff","curve":"stepped"},{"time":2,"color":"ffffffff"}],"attachment":[{"time":0,"name":"faceshield"},{"time":2,"name":"faceshield"}]},"foot1":{"color":[{"time":0,"color":"ffffffff","curve":"stepped"},{"time":2,"color":"ffffffff"}],"attachment":[{"time":0,"name":"foot1_a"},{"time":2,"name":"foot1_a"}]},"foot2":{"color":[{"time":0,"color":"ffffffff","curve":"stepped"},{"time":2,"color":"ffffffff"}],"attachment":[{"time":0,"name":"foot2_a"},{"time":2,"name":"foot2_a"}]},"forearm1":{"color":[{"time":0,"color":"ffffffff","curve":"stepped"},{"time":2,"color":"ffffffff"}],"attachment":[{"time":0,"name":"forearm1_a"},{"time":2,"name":"forearm1_a"}]},"forearm2":{"color":[{"time":0,"color":"ffffffff","curve":"stepped"},{"time":2,"color":"ffffffff"}],"attachment":[{"time":0,"name":"forearm2_a"},{"time":2,"name":"forearm2_a"}]},"hand1":{"color":[{"time":0,"color":"ffffffff","curve":"stepped"},{"time":2,"color":"ffffffff"}],"attachment":[{"time":0,"name":"hand1_b"},{"time":2,"name":"hand1_b"}]},"hand2":{"color":[{"time":0,"color":"ffffffff","curve":"stepped"},{"time":2,"color":"ffffffff"}],"attachment":[{"time":0,"name":"hand2_d"},{"time":2,"name":"hand2_d"}]},"head":{"color":[{"time":0,"color":"ffffffff","curve":"stepped"},{"time":2,"color":"ffffffff"}],"attachment":[{"time":0,"name":"head"},{"time":2,"name":"head"}]},"leg1":{"color":[{"time":0,"color":"ffffffff","curve":"stepped"},{"time":2,"color":"ffffffff"}],"attachment":[{"time":0,"name":"leg1_a"},{"time":2,"name":"leg1_a"}]},"leg2":{"color":[{"time":0,"color":"ffffffff","curve":"stepped"},{"time":2,"color":"ffffffff"}],"attachment":[{"time":0,"name":"leg2_a"},{"time":2,"name":"leg2_a"}]},"mouth":{"color":[{"time":0,"color":"ffffffff","curve":"stepped"},{"time":2,"color":"ffffffff"}],"attachment":[{"time":0,"name":"mouth_b1"},{"time":2,"name":"mouth_b1"}]},"particle1":{"color":[{"time":0,"color":"ffffffff","curve":"stepped"},{"time":2,"color":"ffffffff"}],"attachment":[{"time":0,"name":"particle1"},{"time":2,"name":"particle1"}]},"ponytail3":{"color":[{"time":0,"color":"ffffffff","curve":"stepped"},{"time":2,"color":"ffffffff"}],"attachment":[{"time":0,"name":"ponytail"},{"time":2,"name":"ponytail"}]},"shin1":{"color":[{"time":0,"color":"ffffffff","curve":"stepped"},{"time":2,"color":"ffffffff"}],"attachment":[{"time":0,"name":"shin1_a"},{"time":2,"name":"shin1_a"}]},"shin2":{"color":[{"time":0,"color":"ffffffff","curve":"stepped"},{"time":2,"color":"ffffffff"}],"attachment":[{"time":0,"name":"shin2"},{"time":2,"name":"shin2"}]},"torso1":{"color":[{"time":0,"color":"ffffffff","curve":"stepped"},{"time":2,"color":"ffffffff"}],"attachment":[{"time":0,"name":"torso1"},{"time":2,"name":"torso1"}]},"torso2":{"color":[{"time":0,"color":"ffffffff","curve":"stepped"},{"time":2,"color":"ffffffff"}],"attachment":[{"time":0,"name":"torso2"},{"time":2,"name":"torso2"}]},"torso2_back":{"color":[{"time":0,"color":"ffffffff","curve":"stepped"},{"time":2,"color":"ffffffff"}],"attachment":[{"time":0,"name":"torso2"},{"time":2,"name":"torso2"}]}},"bones":{"antenna":{"rotate":[{"time":0,"angle":0,"curve":[0.37,-0.36,0.792,0.92]},{"time":0.5333,"angle":4,"curve":[0.37,-0.36,0.792,0.92]},{"time":1.0333,"angle":0,"curve":[0.37,-0.36,0.792,0.92]},{"time":1.5333,"angle":4,"curve":[0.37,-0.36,0.792,0.92]},{"time":2,"angle":0}],"translate":[{"time":0,"x":0,"y":0}],"scale":[{"time":0,"x":1,"y":1}]},"forearm1":{"rotate":[{"time":0,"angle":38.49,"curve":[0.322,-1.46,0.822,0.75]},{"time":0.3333,"angle":52.03,"curve":[0.322,-1.46,0.822,0.75]},{"time":0.6666,"angle":38.49,"curve":[0.322,-1.46,0.822,0.75]},{"time":1,"angle":52.03,"curve":[0.322,-1.46,0.822,0.75]},{"time":1.3333,"angle":38.49,"curve":[0.322,-1.46,0.822,0.75]},{"time":1.6666,"angle":52.03,"curve":[0.322,-1.46,0.822,0.75]},{"time":2,"angle":38.49}],"translate":[{"time":0,"x":0,"y":0}],"scale":[{"time":0,"x":1,"y":1}]},"leg1":{"rotate":[{"time":0,"angle":-0.22,"curve":[0.375,-0.49,0.788,0.87]},{"time":0.5,"angle":3,"curve":[0.375,-0.49,0.788,0.87]},{"time":1,"angle":-0.22,"curve":[0.375,-0.49,0.788,0.87]},{"time":1.5,"angle":3,"curve":[0.375,-0.49,0.788,0.87]},{"time":2,"angle":-0.22}],"translate":[{"time":0,"x":4.4,"y":14.68,"curve":[0.375,-0.49,0.788,0.87]},{"time":0.5,"x":4.4,"y":12.8,"curve":[0.375,-0.49,0.788,0.87]},{"time":1,"x":4.4,"y":14.68,"curve":[0.375,-0.49,0.788,0.87]},{"time":1.5,"x":4.4,"y":12.8,"curve":[0.375,-0.49,0.788,0.87]},{"time":2,"x":4.4,"y":14.68}],"scale":[{"time":0,"x":1,"y":1}]},"shin1":{"rotate":[{"time":0,"angle":-2.22,"curve":[0.375,-0.49,0.788,0.87]},{"time":0.5,"angle":-369.92,"curve":[0.375,-0.49,0.788,0.87]},{"time":1,"angle":-2.22,"curve":[0.375,-0.49,0.788,0.87]},{"time":1.5,"angle":-369.92,"curve":[0.375,-0.49,0.788,0.87]},{"time":2,"angle":-2.22}],"translate":[{"time":0,"x":4.25,"y":0.97,"curve":[0.375,-0.49,0.788,0.87]},{"time":0.5,"x":2.68,"y":0.97,"curve":[0.375,-0.49,0.788,0.87]},{"time":1,"x":4.25,"y":0.97,"curve":[0.375,-0.49,0.788,0.87]},{"time":1.5,"x":2.68,"y":0.97,"curve":[0.375,-0.49,0.788,0.87]},{"time":2,"x":4.25,"y":0.97}],"scale":[{"time":0,"x":1,"y":1}]},"leg2":{"rotate":[{"time":0,"angle":12.94,"curve":[0.486,-0.22,0.762,1]},{"time":0.5,"angle":14.81,"curve":[0.486,-0.22,0.762,1]},{"time":1,"angle":12.94,"curve":[0.486,-0.22,0.762,1]},{"time":1.5,"angle":14.81,"curve":[0.486,-0.22,0.762,1]},{"time":2,"angle":12.94}],"translate":[{"time":0,"x":0.45,"y":6.35,"curve":[0.486,-0.22,0.762,1]},{"time":0.5,"x":0.45,"y":4.71,"curve":[0.486,-0.22,0.762,1]},{"time":1,"x":0.45,"y":6.35,"curve":[0.486,-0.22,0.762,1]},{"time":1.5,"x":0.45,"y":4.71,"curve":[0.486,-0.22,0.762,1]},{"time":2,"x":0.45,"y":6.35}],"scale":[{"time":0,"x":1,"y":1}]},"foot1":{"rotate":[{"time":0,"angle":6.93,"curve":[0.375,-0.49,0.788,0.87]},{"time":0.5,"angle":8.36,"curve":[0.375,-0.49,0.788,0.87]},{"time":1,"angle":6.93,"curve":[0.375,-0.49,0.788,0.87]},{"time":1.5,"angle":8.36,"curve":[0.375,-0.49,0.788,0.87]},{"time":2,"angle":6.93}],"translate":[{"time":0,"x":-1.54,"y":1.72}],"scale":[{"time":0,"x":1,"y":1}]},"hand1":{"rotate":[{"time":0,"angle":12.06,"curve":[0.19,0.24,0.63,1.5]},{"time":0.3333,"angle":-2.89,"curve":[0.19,0.24,0.63,1.5]},{"time":0.6666,"angle":12.06,"curve":[0.19,0.24,0.63,1.5]},{"time":1,"angle":-2.89,"curve":[0.19,0.24,0.63,1.5]},{"time":1.3333,"angle":12.06,"curve":[0.19,0.24,0.63,1.5]},{"time":1.6666,"angle":-2.89,"curve":[0.19,0.24,0.63,1.5]},{"time":2,"angle":12.06}],"translate":[{"time":0,"x":-4.94,"y":-1.46}],"scale":[{"time":0,"x":1,"y":1}]},"head":{"rotate":[{"time":0,"angle":-10.66,"curve":[0.394,-0.69,0.803,0.81]},{"time":0.5333,"angle":-11.7,"curve":[0.394,-0.69,0.803,0.81]},{"time":1.0333,"angle":-10.66,"curve":[0.394,-0.69,0.803,0.81]},{"time":1.5333,"angle":-11.7,"curve":[0.394,-0.69,0.803,0.81]},{"time":2,"angle":-10.66}],"translate":[{"time":0,"x":-5,"y":-5.34}],"scale":[{"time":0,"x":1,"y":1}]},"foot2":{"rotate":[{"time":0,"angle":3.58,"curve":[0.25,0,0.345,1]},{"time":0.5,"angle":-353.15,"curve":[0.25,0,0.345,1]},{"time":1,"angle":-356.41,"curve":[0.25,0,0.345,1]},{"time":1.5,"angle":-353.15,"curve":[0.25,0,0.345,1]},{"time":2,"angle":-356.41}],"translate":[{"time":0,"x":0.76,"y":1.25,"curve":[0.25,0,0.345,1]},{"time":0.5,"x":-0.48,"y":1.08,"curve":[0.25,0,0.345,1]},{"time":1,"x":0.76,"y":1.25,"curve":[0.25,0,0.345,1]},{"time":1.5,"x":-0.48,"y":1.08,"curve":[0.25,0,0.345,1]},{"time":2,"x":0.76,"y":1.25}],"scale":[{"time":0,"x":1,"y":1}]},"shin2":{"rotate":[{"time":0,"angle":-14.92,"curve":[0.486,-0.22,0.762,1]},{"time":0.5,"angle":-382.82,"curve":[0.486,-0.22,0.762,1]},{"time":1,"angle":-374.92,"curve":[0.486,-0.22,0.762,1]},{"time":1.5,"angle":-382.82,"curve":[0.486,-0.22,0.762,1]},{"time":2,"angle":-374.92}],"translate":[{"time":0,"x":-10.11,"y":1.92}],"scale":[{"time":0,"x":1,"y":1}]},"arm1":{"rotate":[{"time":0,"angle":166.2,"curve":[0.196,0.28,0.598,1.84]},{"time":0.3333,"angle":-200.98,"curve":[0.196,0.28,0.598,1.84]},{"time":0.6666,"angle":-193.79,"curve":[0.196,0.28,0.598,1.84]},{"time":1,"angle":-200.98,"curve":[0.196,0.28,0.598,1.84]},{"time":1.3333,"angle":-193.79,"curve":[0.196,0.28,0.598,1.84]},{"time":1.6666,"angle":-200.98,"curve":[0.196,0.28,0.598,1.84]},{"time":2,"angle":-193.79}],"translate":[{"time":0,"x":-8.89,"y":-2.18}],"scale":[{"time":0,"x":1,"y":1}]},"torso":{"rotate":[{"time":0,"angle":2.2}],"translate":[{"time":0,"x":0.22,"y":9.43,"curve":[0.407,-0.53,0.825,0.85]},{"time":0.5,"x":0.22,"y":7.81,"curve":[0.407,-0.53,0.825,0.85]},{"time":1,"x":0.22,"y":9.43,"curve":[0.407,-0.53,0.825,0.85]},{"time":1.5,"x":0.22,"y":7.81,"curve":[0.407,-0.53,0.825,0.85]},{"time":2,"x":0.22,"y":9.43}],"scale":[{"time":0,"x":1,"y":1,"curve":[0.193,0.2,0.668,1.56]},{"time":0.5,"x":0.975,"y":1,"curve":[0.193,0.2,0.668,1.56]},{"time":1,"x":1,"y":1,"curve":[0.193,0.2,0.668,1.56]},{"time":1.5,"x":0.975,"y":1,"curve":[0.193,0.2,0.668,1.56]},{"time":2,"x":1,"y":1}]},"root":{"rotate":[{"time":0,"angle":0}],"translate":[{"time":0,"x":0,"y":0}],"scale":[{"time":0,"x":1,"y":1}]},"body":{"rotate":[{"time":0,"angle":0}],"translate":[{"time":0,"x":0,"y":-3.63}],"scale":[{"time":0,"x":1,"y":1}]},"clavicle1":{"rotate":[{"time":0,"angle":2.94}],"translate":[{"time":0,"x":-8.17,"y":-9.97,"curve":[0.352,-0.47,0.818,0.73]},{"time":0.5333,"x":-10.54,"y":-9.88,"curve":[0.352,-0.47,0.818,0.73]},{"time":1.0333,"x":-8.17,"y":-9.97,"curve":[0.352,-0.47,0.818,0.73]},{"time":1.5333,"x":-10.54,"y":-9.88,"curve":[0.352,-0.47,0.818,0.73]},{"time":2,"x":-8.17,"y":-9.97}],"scale":[{"time":0,"x":1,"y":1}]},"cog":{"rotate":[{"time":0,"angle":0}],"translate":[{"time":0,"x":20.52,"y":2.3}],"scale":[{"time":0,"x":1,"y":1}]},"particles_foot_bone":{"rotate":[{"time":0,"angle":0}],"translate":[{"time":0,"x":0,"y":0}],"scale":[{"time":0,"x":1,"y":1}]},"influence_bone":{"rotate":[{"time":0,"angle":0}],"translate":[{"time":0,"x":0,"y":0}],"scale":[{"time":0,"x":1,"y":1}]},"tail":{"rotate":[{"time":0,"angle":0.63,"curve":[0.196,0.19,0.684,1.56]},{"time":0.5333,"angle":-353.87,"curve":[0.196,0.19,0.684,1.56]},{"time":1.0333,"angle":-359.36,"curve":[0.196,0.19,0.684,1.56]},{"time":1.5333,"angle":-353.87,"curve":[0.196,0.19,0.684,1.56]},{"time":2,"angle":-359.36}],"translate":[{"time":0,"x":0,"y":0}],"scale":[{"time":0,"x":1,"y":1}]},"clavicle2":{"rotate":[{"time":0,"angle":0}],"translate":[{"time":0,"x":0,"y":0,"curve":[0.415,-0.85,0.801,0.8]},{"time":0.5,"x":-5.52,"y":0.2,"curve":[0.415,-0.85,0.801,0.8]},{"time":1,"x":0,"y":0,"curve":[0.415,-0.85,0.801,0.8]},{"time":1.5,"x":-5.52,"y":0.2,"curve":[0.415,-0.85,0.801,0.8]},{"time":2,"x":0,"y":0}],"scale":[{"time":0,"x":1,"y":1}]},"arm2":{"rotate":[{"time":0,"angle":5.91,"curve":[0.352,-1.13,0.818,0.78]},{"time":0.5333,"angle":5.95,"curve":[0.352,-1.13,0.818,0.78]},{"time":1.0333,"angle":5.91,"curve":[0.352,-1.13,0.818,0.78]},{"time":1.5333,"angle":5.95,"curve":[0.352,-1.13,0.818,0.78]},{"time":2,"angle":5.91}],"translate":[{"time":0,"x":0,"y":0}],"scale":[{"time":0,"x":1,"y":1}]},"forearm2":{"rotate":[{"time":0,"angle":39.21,"curve":[0.352,-1.13,0.818,0.78]},{"time":0.5333,"angle":46.89,"curve":[0.352,-1.13,0.818,0.78]},{"time":1.0333,"angle":39.21,"curve":[0.352,-1.13,0.818,0.78]},{"time":1.5333,"angle":46.89,"curve":[0.352,-1.13,0.818,0.78]},{"time":2,"angle":39.21}],"translate":[{"time":0,"x":0,"y":0}],"scale":[{"time":0,"x":1,"y":1}]},"hand2":{"rotate":[{"time":0,"angle":4.35}],"translate":[{"time":0,"x":0,"y":0}],"scale":[{"time":0,"x":1,"y":1}]}},"drawOrder":[{"time":0,"offsets":[{"slot":"arm1","offset":22},{"slot":"hand1","offset":22},{"slot":"forearm1","offset":22}]},{"time":2,"offsets":[{"slot":"arm1","offset":22},{"slot":"hand1","offset":22},{"slot":"forearm1","offset":22}]}]},"win":{"slots":{"antenna":{"color":[{"time":0,"color":"ffffffff","curve":"stepped"},{"time":4,"color":"ffffffff"}],"attachment":[{"time":0,"name":"antenna"},{"time":4,"name":"antenna"}]},"appear_blue":{"color":[{"time":0,"color":"ffffffff","curve":"stepped"},{"time":4,"color":"ffffffff"}],"attachment":[{"time":0,"name":null},{"time":4,"name":null}]},"appear_mag":{"color":[{"time":0,"color":"ffffffff","curve":"stepped"},{"time":4,"color":"ffffffff"}],"attachment":[{"time":0,"name":null},{"time":4,"name":null}]},"arm1":{"color":[{"time":0,"color":"ffffffff","curve":"stepped"},{"time":4,"color":"ffffffff"}],"attachment":[{"time":0,"name":"arm1_a"},{"time":4,"name":"arm1_a"}]},"arm2":{"color":[{"time":0,"color":"ffffffff","curve":"stepped"},{"time":4,"color":"ffffffff"}],"attachment":[{"time":0,"name":"arm2"},{"time":4,"name":"arm2"}]},"cheer_flag":{"color":[{"time":0,"color":"ffffffff","curve":"stepped"},{"time":4,"color":"ffffffff"}],"attachment":[{"time":0,"name":null},{"time":4,"name":null}]},"cheer_glove":{"attachment":[{"time":0,"name":null},{"time":4,"name":null}]},"eyes":{"color":[{"time":0,"color":"ffffffff","curve":"stepped"},{"time":4,"color":"ffffffff"}],"attachment":[{"time":0,"name":"eyes_e1"},{"time":1.6,"name":"eyes_h2"},{"time":2.1,"name":"eyes_e1"},{"time":2.6666,"name":"eyes_h2"},{"time":2.8333,"name":"eyes_h2"},{"time":3.1,"name":"eyes_e1"},{"time":4,"name":"eyes_e1"}]},"faceshield":{"color":[{"time":0,"color":"ffffffff","curve":"stepped"},{"time":4,"color":"ffffffff"}],"attachment":[{"time":0,"name":"faceshield"},{"time":4,"name":"faceshield"}]},"foot1":{"color":[{"time":0,"color":"ffffffff","curve":"stepped"},{"time":4,"color":"ffffffff"}],"attachment":[{"time":0,"name":"foot1_a"},{"time":4,"name":"foot1_a"}]},"foot2":{"color":[{"time":0,"color":"ffffffff","curve":"stepped"},{"time":4,"color":"ffffffff"}],"attachment":[{"time":0,"name":"foot2_a"},{"time":4,"name":"foot2_a"}]},"forearm1":{"color":[{"time":0,"color":"ffffffff","curve":"stepped"},{"time":4,"color":"ffffffff"}],"attachment":[{"time":0,"name":"forearm1_a"},{"time":4,"name":"forearm1_a"}]},"forearm2":{"color":[{"time":0,"color":"ffffffff","curve":"stepped"},{"time":4,"color":"ffffffff"}],"attachment":[{"time":0,"name":"forearm2_a"},{"time":4,"name":"forearm2_a"}]},"hand1":{"color":[{"time":0,"color":"ffffffff","curve":"stepped"},{"time":4,"color":"ffffffff"}],"attachment":[{"time":0,"name":"hand1_a"},{"time":4,"name":"hand1_a"}]},"hand2":{"color":[{"time":0,"color":"ffffffff","curve":"stepped"},{"time":4,"color":"ffffffff"}],"attachment":[{"time":0,"name":"hand2_g"},{"time":1.8,"name":"hand2_f"},{"time":2.7,"name":"hand2_g"},{"time":4,"name":"hand2_g"}]},"head":{"color":[{"time":0,"color":"ffffffff","curve":"stepped"},{"time":4,"color":"ffffffff"}],"attachment":[{"time":0,"name":"head"},{"time":4,"name":"head"}]},"leg1":{"color":[{"time":0,"color":"ffffffff","curve":"stepped"},{"time":4,"color":"ffffffff"}],"attachment":[{"time":0,"name":"leg1_a"},{"time":4,"name":"leg1_a"}]},"leg2":{"color":[{"time":0,"color":"ffffffff","curve":"stepped"},{"time":4,"color":"ffffffff"}],"attachment":[{"time":0,"name":"leg2_a"},{"time":4,"name":"leg2_a"}]},"mouth":{"color":[{"time":0,"color":"ffffffff","curve":"stepped"},{"time":4,"color":"ffffffff"}],"attachment":[{"time":0,"name":"mouth_b1"},{"time":1.8666,"name":"mouth_a1"},{"time":3.2333,"name":"mouth_b1"},{"time":4,"name":"mouth_b1"}]},"particle1":{"color":[{"time":0,"color":"ffffffff","curve":"stepped"},{"time":4,"color":"ffffffff"}],"attachment":[{"time":0,"name":"particle1"},{"time":4,"name":"particle1"}]},"ponytail3":{"color":[{"time":0,"color":"ffffffff","curve":"stepped"},{"time":4,"color":"ffffffff"}],"attachment":[{"time":0,"name":"ponytail"},{"time":4,"name":"ponytail"}]},"shin1":{"color":[{"time":0,"color":"ffffffff","curve":"stepped"},{"time":4,"color":"ffffffff"}],"attachment":[{"time":0,"name":"shin1_a"},{"time":4,"name":"shin1_a"}]},"shin2":{"color":[{"time":0,"color":"ffffffff","curve":"stepped"},{"time":4,"color":"ffffffff"}],"attachment":[{"time":0,"name":"shin2"},{"time":4,"name":"shin2"}]},"torso1":{"color":[{"time":0,"color":"ffffffff","curve":"stepped"},{"time":4,"color":"ffffffff"}],"attachment":[{"time":0,"name":"torso1"},{"time":4,"name":"torso1"}]},"torso2":{"color":[{"time":0,"color":"ffffffff","curve":"stepped"},{"time":4,"color":"ffffffff"}],"attachment":[{"time":0,"name":"torso2"},{"time":4,"name":"torso2"}]},"torso2_back":{"color":[{"time":0,"color":"ffffffff","curve":"stepped"},{"time":4,"color":"ffffffff"}],"attachment":[{"time":0,"name":"torso2"},{"time":4,"name":"torso2"}]}},"bones":{"hand1":{"rotate":[{"time":0,"angle":0,"curve":[0.233,0.15,0.72,1.54]},{"time":0.5333,"angle":9.89,"curve":[0.233,0.15,0.72,1.54]},{"time":1.0333,"angle":0,"curve":[0.233,0.15,0.72,1.54]},{"time":1.5333,"angle":9.89,"curve":[0.233,0.15,0.72,1.54]},{"time":2.0333,"angle":0,"curve":[0.233,0.15,0.72,1.54]},{"time":2.5333,"angle":9.89,"curve":[0.233,0.15,0.72,1.54]},{"time":3.0333,"angle":0,"curve":[0.233,0.15,0.72,1.54]},{"time":3.5333,"angle":9.89,"curve":[0.233,0.15,0.72,1.54]},{"time":4,"angle":0}],"translate":[{"time":0,"x":-4.23,"y":0}],"scale":[{"time":0,"x":1,"y":1}]},"torso":{"rotate":[{"time":0,"angle":8.06,"curve":"stepped"},{"time":1.4,"angle":8.06,"curve":[0.54,-0.47,0.639,1]},{"time":1.9666,"angle":12.72,"curve":"stepped"},{"time":2.3666,"angle":12.72,"curve":[0.25,0,0.75,1]},{"time":3,"angle":8.06}],"translate":[{"time":0,"x":4.25,"y":8.08,"curve":[0.404,-0.69,0.789,0.82]},{"time":0.5,"x":4.25,"y":4.69,"curve":[0.404,-0.69,0.789,0.82]},{"time":1,"x":4.25,"y":8.08,"curve":[0.404,-0.69,0.789,0.82]},{"time":1.5,"x":4.25,"y":4.69,"curve":[0.404,-0.69,0.789,0.82]},{"time":2,"x":4.25,"y":8.08,"curve":[0.404,-0.69,0.789,0.82]},{"time":2.5,"x":4.25,"y":4.69,"curve":[0.404,-0.69,0.789,0.82]},{"time":3,"x":4.25,"y":8.08,"curve":[0.404,-0.69,0.789,0.82]},{"time":3.5,"x":4.25,"y":4.69,"curve":[0.404,-0.69,0.789,0.82]},{"time":4,"x":4.25,"y":8.08}],"scale":[{"time":0,"x":1,"y":1,"curve":[0.273,-0.81,0.834,0.77]},{"time":0.5,"x":0.944,"y":1,"curve":[0.25,0,0.75,1]},{"time":1,"x":1,"y":1,"curve":[0.255,-0.88,0.723,0.32]},{"time":1.4,"x":0.966,"y":1,"curve":[0.632,0,0.81,0.85]},{"time":1.7,"x":0.837,"y":1,"curve":[0.216,0.12,0.501,1.66]},{"time":2,"x":1,"y":1,"curve":"stepped"},{"time":2.3666,"x":1,"y":1,"curve":[0.487,0,0.75,1]},{"time":2.7,"x":0.898,"y":1,"curve":[0.114,0.17,0.614,1.24]},{"time":3,"x":1,"y":1,"curve":[0.273,-0.81,0.834,0.77]},{"time":3.5,"x":0.944,"y":1,"curve":[0.25,0,0.75,1]},{"time":4,"x":1,"y":1}]},"shin1":{"rotate":[{"time":0,"angle":-30.93}],"translate":[{"time":0,"x":-3.5,"y":5.3}],"scale":[{"time":0,"x":1,"y":1}]},"foot2":{"rotate":[{"time":0,"angle":2.04}],"translate":[{"time":0,"x":-0.17,"y":0.04}],"scale":[{"time":0,"x":1,"y":1}]},"leg1":{"rotate":[{"time":0,"angle":5.95}],"translate":[{"time":0,"x":8.04,"y":9}],"scale":[{"time":0,"x":1,"y":1}]},"forearm2":{"rotate":[{"time":0,"angle":25.3,"curve":"stepped"},{"time":1.4333,"angle":25.3,"curve":[0.358,-1.8,0.816,0.65]},{"time":1.7666,"angle":43.76,"curve":[0.469,-0.74,0.681,1]},{"time":2.0666,"angle":-12.77,"curve":[0.25,0,0.75,1]},{"time":2.3333,"angle":-17.19,"curve":[0.354,-0.64,0.75,1]},{"time":2.6,"angle":-12.77,"curve":[0.327,-0.9,0.764,0.96]},{"time":3.0333,"angle":44.66,"curve":[0.402,-0.33,0.75,1]},{"time":3.5333,"angle":25.3}],"translate":[{"time":0,"x":-1.73,"y":-0.21}],"scale":[{"time":0,"x":1,"y":1}]},"forearm1":{"rotate":[{"time":0,"angle":74.17,"curve":[0.233,0.15,0.72,1.54]},{"time":0.5333,"angle":69.8,"curve":[0.233,0.15,0.72,1.54]},{"time":1,"angle":74.17,"curve":[0.233,0.15,0.72,1.54]},{"time":1.5333,"angle":69.8,"curve":[0.233,0.15,0.72,1.54]},{"time":1.8666,"angle":74.17,"curve":[0.22,0.14,0.595,1.61]},{"time":2.3333,"angle":78.03,"curve":[0.25,0,0.75,1]},{"time":3,"angle":74.17,"curve":[0.233,0.15,0.72,1.54]},{"time":3.5333,"angle":69.8,"curve":[0.233,0.15,0.72,1.54]},{"time":4,"angle":74.17}],"translate":[{"time":0,"x":0,"y":0}],"scale":[{"time":0,"x":1,"y":1}]},"root":{"rotate":[{"time":0,"angle":0}],"translate":[{"time":0,"x":0,"y":0}],"scale":[{"time":0,"x":1,"y":1}]},"head":{"rotate":[{"time":0,"angle":-13.32,"curve":[0.341,-1.27,0.82,0.7]},{"time":0.5333,"angle":-15.66,"curve":[0.341,-1.27,0.82,0.7]},{"time":1,"angle":-13.32,"curve":[0.341,-1.27,0.82,0.7]},{"time":1.5333,"angle":-15.66,"curve":[0.25,0,0.393,1.67]},{"time":2.1,"angle":0.07,"curve":[0.199,0.08,0.497,1]},{"time":2.5333,"angle":-2.97,"curve":[0.25,0,0.486,1.42]},{"time":3.0333,"angle":-13.32,"curve":[0.341,-1.27,0.82,0.7]},{"time":3.5333,"angle":-15.66,"curve":[0.341,-1.27,0.82,0.7]},{"time":4,"angle":-13.32}],"translate":[{"time":0,"x":0,"y":0,"curve":[0.25,0,0.75,1]},{"time":0.5333,"x":-2.97,"y":0.42,"curve":[0.25,0,0.75,1]},{"time":1,"x":0,"y":0,"curve":[0.25,0,0.75,1]},{"time":1.5333,"x":-2.97,"y":0.42,"curve":[0.25,0,0.75,1]},{"time":2.0333,"x":0,"y":0,"curve":[0.25,0,0.75,1]},{"time":2.5333,"x":-2.97,"y":0.42,"curve":[0.25,0,0.75,1]},{"time":3.0333,"x":0,"y":0,"curve":[0.25,0,0.75,1]},{"time":3.5333,"x":-2.97,"y":0.42,"curve":[0.25,0,0.75,1]},{"time":4,"x":0,"y":0}],"scale":[{"time":0,"x":1,"y":1}]},"hand2":{"rotate":[{"time":0,"angle":63.89,"curve":[0.323,-0.73,0.823,0.77]},{"time":0.5333,"angle":55.43,"curve":[0.323,-0.73,0.823,0.77]},{"time":1.0333,"angle":63.89,"curve":[0.323,-0.73,0.823,0.77]},{"time":1.4,"angle":55.43,"curve":[0.323,-0.73,0.823,0.77]},{"time":1.7333,"angle":26.15,"curve":[0.224,0.18,0.649,1.57]},{"time":2.0666,"angle":-10.28,"curve":"stepped"},{"time":2.5333,"angle":-10.28,"curve":[0.323,-0.73,0.823,0.77]},{"time":3.0333,"angle":14.08,"curve":[0.25,0,0.75,1]},{"time":3.5333,"angle":55.43,"curve":[0.323,-0.73,0.823,0.77]},{"time":4,"angle":63.89}],"translate":[{"time":0,"x":0,"y":0}],"scale":[{"time":0,"x":1,"y":1}]},"arm1":{"rotate":[{"time":0,"angle":-60.95,"curve":[0.233,0.15,0.72,1.54]},{"time":0.5333,"angle":-57.36,"curve":[0.233,0.15,0.72,1.54]},{"time":1.0333,"angle":-60.95,"curve":[0.233,0.15,0.72,1.54]},{"time":1.5333,"angle":-57.36,"curve":[0.233,0.15,0.72,1.54]},{"time":1.8666,"angle":-60.95,"curve":[0.22,0.14,0.595,1.61]},{"time":2.3333,"angle":-49.67,"curve":[0.25,0,0.75,1]},{"time":3,"angle":-60.95,"curve":[0.233,0.15,0.72,1.54]},{"time":3.5333,"angle":-57.36,"curve":[0.233,0.15,0.72,1.54]},{"time":4,"angle":-60.95}],"translate":[{"time":0,"x":-8.89,"y":-2.18}],"scale":[{"time":0,"x":1,"y":1}]},"antenna":{"rotate":[{"time":0,"angle":0,"curve":[0.356,-0.78,0.75,1]},{"time":0.5333,"angle":7.63,"curve":[0.356,-0.78,0.75,1]},{"time":1.0333,"angle":0,"curve":[0.356,-0.78,0.75,1]},{"time":1.5333,"angle":7.63,"curve":[0.356,-0.78,0.75,1]},{"time":2.0333,"angle":0,"curve":[0.356,-0.78,0.75,1]},{"time":2.5333,"angle":7.63,"curve":[0.356,-0.78,0.75,1]},{"time":3.0333,"angle":0,"curve":[0.356,-0.78,0.75,1]},{"time":3.5333,"angle":7.63,"curve":[0.356,-0.78,0.75,1]},{"time":4,"angle":0}],"translate":[{"time":0,"x":0,"y":0}],"scale":[{"time":0,"x":1,"y":1}]},"foot1":{"rotate":[{"time":0,"angle":4.21}],"translate":[{"time":0,"x":-1.22,"y":0.78}],"scale":[{"time":0,"x":1,"y":1}]},"arm2":{"rotate":[{"time":0,"angle":46.31,"curve":[0.32,-0.88,0.839,0.69]},{"time":0.5333,"angle":36.49,"curve":[0.32,-0.88,0.839,0.69]},{"time":1.0333,"angle":46.31,"curve":[0.32,-0.88,0.839,0.69]},{"time":1.4333,"angle":36.49,"curve":[0.32,-0.88,0.839,0.69]},{"time":2.0666,"angle":63.04,"curve":"stepped"},{"time":2.5333,"angle":63.04,"curve":[0.153,0.21,0.432,1.78]},{"time":3.0333,"angle":46.31,"curve":[0.32,-0.88,0.839,0.69]},{"time":3.5333,"angle":36.49,"curve":[0.32,-0.88,0.839,0.69]},{"time":4,"angle":46.31}],"translate":[{"time":0,"x":-6.63,"y":5.67}],"scale":[{"time":0,"x":1,"y":1}]},"shin2":{"rotate":[{"time":0,"angle":5.32}],"translate":[{"time":0,"x":-3.87,"y":0.1}],"scale":[{"time":0,"x":1,"y":1}]},"leg2":{"rotate":[{"time":0,"angle":-7.48}],"translate":[{"time":0,"x":1.23,"y":10.64}],"scale":[{"time":0,"x":1,"y":1}]},"body":{"rotate":[{"time":0,"angle":0}],"translate":[{"time":0,"x":0,"y":-3.63}],"scale":[{"time":0,"x":1,"y":1}]},"cog":{"rotate":[{"time":0,"angle":0}],"translate":[{"time":0,"x":20.52,"y":2.3}],"scale":[{"time":0,"x":1,"y":1}]},"clavicle2":{"rotate":[{"time":0,"angle":-7.39,"curve":"stepped"},{"time":1.4,"angle":-7.39,"curve":[0.126,0.18,0.37,1.78]},{"time":2.0666,"angle":-18.69,"curve":"stepped"},{"time":2.5333,"angle":-18.69,"curve":[0.25,0,0.75,1]},{"time":2.9666,"angle":-7.39}],"translate":[{"time":0,"x":-5.84,"y":5.71,"curve":[0.379,-0.76,0.783,0.87]},{"time":0.5,"x":-8.36,"y":6.06,"curve":[0.379,-0.76,0.783,0.87]},{"time":1,"x":-5.84,"y":5.71,"curve":[0.357,-0.79,0.733,0.4]},{"time":1.4,"x":-7.53,"y":5.95,"curve":[0.375,0.51,0.712,0.89]},{"time":2.0666,"x":-1,"y":16.93,"curve":"stepped"},{"time":2.5333,"x":-1,"y":16.93,"curve":[0.178,0.22,0.7,1.52]},{"time":2.9666,"x":-5.84,"y":5.71,"curve":[0.379,-0.76,0.783,0.87]},{"time":3.4666,"x":-8.36,"y":6.06,"curve":[0.379,-0.76,0.783,0.87]},{"time":3.9666,"x":-5.84,"y":5.71}],"scale":[{"time":0,"x":1,"y":1}]},"clavicle1":{"rotate":[{"time":0,"angle":-2.63,"curve":"stepped"},{"time":1.8333,"angle":-2.63,"curve":[0.467,-0.78,0.77,0.82]},{"time":2.3,"angle":5.3,"curve":[0.373,-0.92,0.791,0.81]},{"time":2.9666,"angle":-2.63}],"translate":[{"time":0,"x":-0.44,"y":1.53,"curve":[0.379,-0.76,0.783,0.87]},{"time":0.5,"x":-2.96,"y":1.88,"curve":[0.379,-0.76,0.783,0.87]},{"time":1,"x":-0.44,"y":1.53,"curve":[0.379,-0.76,0.783,0.87]},{"time":1.5,"x":-2.96,"y":1.88,"curve":[0.379,-0.76,0.783,0.87]},{"time":1.8333,"x":-0.44,"y":1.53,"curve":[0.467,-0.78,0.77,0.82]},{"time":2.3,"x":-5.76,"y":1.66,"curve":[0.25,0,0.75,1]},{"time":2.9666,"x":-0.44,"y":1.53,"curve":[0.202,0.24,0.715,1.56]},{"time":3.4666,"x":-2.96,"y":1.88,"curve":[0.379,-0.76,0.783,0.87]},{"time":3.9666,"x":-0.44,"y":1.53}],"scale":[{"time":0,"x":1,"y":1}]},"particles_foot_bone":{"rotate":[{"time":0,"angle":0}],"translate":[{"time":0,"x":0,"y":0}],"scale":[{"time":0,"x":1,"y":1}]},"influence_bone":{"rotate":[{"time":0,"angle":0}],"translate":[{"time":0,"x":0,"y":0}],"scale":[{"time":0,"x":1,"y":1}]},"tail":{"rotate":[{"time":0,"angle":-3.75,"curve":[0.21,0.48,0.624,1.7]},{"time":0.5333,"angle":-0.3,"curve":[0.21,0.48,0.624,1.7]},{"time":1,"angle":-3.75,"curve":[0.21,0.48,0.624,1.7]},{"time":1.5333,"angle":-0.3,"curve":[0.408,-0.83,0.781,0.84]},{"time":2,"angle":-352.79,"curve":[0.423,-0.41,0.82,0.77]},{"time":2.3333,"angle":-8.24,"curve":[0.318,-0.81,0.75,1]},{"time":2.6666,"angle":-16.15,"curve":[0.439,-0.31,0.75,1]},{"time":3.0333,"angle":-3.75,"curve":[0.21,0.48,0.624,1.7]},{"time":3.5333,"angle":-0.3,"curve":[0.21,0.48,0.624,1.7]},{"time":4,"angle":-3.75}],"translate":[{"time":0,"x":0,"y":0}],"scale":[{"time":0,"x":1,"y":1}]}},"drawOrder":[{"time":0,"offsets":[{"slot":"hand1","offset":-4},{"slot":"forearm1","offset":5}]},{"time":4,"offsets":[{"slot":"hand1","offset":-4},{"slot":"forearm1","offset":5}]}]}}}