{"frames": [

{
	"filename": "blueBtn",
	"frame": {"x":1530,"y":248,"w":481,"h":205},
	"rotated": false,
	"trimmed": true,
	"spriteSourceSize": {"x":1,"y":1,"w":481,"h":205},
	"sourceSize": {"w":482,"h":208}
},
{
	"filename": "questionBox",
	"frame": {"x":1,"y":1,"w":1657,"h":245},
	"rotated": false,
	"trimmed": false,
	"spriteSourceSize": {"x":0,"y":0,"w":1657,"h":245},
	"sourceSize": {"w":1657,"h":245}
},
{
	"filename": "questionBtn",
	"frame": {"x":1530,"y":455,"w":435,"h":139},
	"rotated": false,
	"trimmed": true,
	"spriteSourceSize": {"x":30,"y":30,"w":435,"h":139},
	"sourceSize": {"w":465,"h":199}
},
{
	"filename": "questionImage",
	"frame": {"x":1,"y":248,"w":1527,"h":385},
	"rotated": false,
	"trimmed": false,
	"spriteSourceSize": {"x":0,"y":0,"w":1527,"h":385},
	"sourceSize": {"w":1527,"h":385}
}],
"meta": {
	"app": "https://www.codeandweb.com/texturepacker",
	"version": "1.0",
	"image": "atlas.png",
	"format": "RGBA8888",
	"size": {"w":2012,"h":634},
	"scale": "1",
	"smartupdate": "$TexturePacker:SmartUpdate:772d94c8963c347ae83007ae515e5a6b:6e799bdcb709bcfae27939e36ab8c527:cbce6b53f0f49e0bf15173c25c41f876$"
}
}
