{
  "startColorAlpha" : 1,
  "startParticleSizeVariance" : 16.11688,
  "startColorGreen" : 1,
  "rotatePerSecond" : 0,
  "radialAcceleration" : 0,
  "yCoordFlipped" : -1,
  "emitterType" : 0,
  "blendFuncSource" : 770,
  "finishColorVarianceAlpha" : 0,
  "rotationEnd" : 0,
  "startColorVarianceBlue" : 0,
  "rotatePerSecondVariance" : 0,
  "particleLifespan" : 0.7551619,
  "minRadius" : 0,
  "configName" : "normalChargeEarth48",
  "tangentialAcceleration" : 0,
  "rotationStart" : 0,
  "startColorVarianceGreen" : 0,
  "speed" : 200,
  "minRadiusVariance" : 0,
  "finishColorVarianceBlue" : 0,
  "finishColorBlue" : 1,
  "finishColorGreen" : 1,
  "blendFuncDestination" : 771,
  "finishColorAlpha" : 1,
  "sourcePositionVariancex" : 100,
  "startParticleSize" : 21.19481,
  "sourcePositionVariancey" : 10,
  "startColorRed" : 0.9999928,
  "finishColorVarianceRed" : 0,
  "absolutePosition" : false,
  "textureFileName" : "normalChargeEarth48.png",
  "startColorVarianceAlpha" : 0,
  "maxParticles" : 25,
  "finishColorVarianceGreen" : 0,
  "finishParticleSize" : 0,
  "duration" : -1,
  "startColorVarianceRed" : 0,
  "finishColorRed" : 0.999996,
  "gravityx" : 0,
  "maxRadiusVariance" : 3,
  "finishParticleSizeVariance" : 0,
  "gravityy" : 185.9781,
  "rotationEndVariance" : 778.5511,
  "startColorBlue" : 1,
  "rotationStartVariance" : 298.7642,
  "speedVariance" : 92.38027,
  "radialAccelVariance" : 0,
  "textureImageData" : "",
  "tangentialAccelVariance" : -0,
  "particleLifespanVariance" : 0.5,
  "angleVariance" : -47.21895,
  "angle" : -90,
  "maxRadius" : 367.3711
}