{
  "startColorAlpha" : 1,
  "startParticleSizeVariance" : 0,
  "startColorGreen" : 1,
  "rotatePerSecond" : 360,
  "radialAcceleration" : -2000,
  "yCoordFlipped" : -1,
  "emitterType" : 0,
  "blendFuncSource" : 1,
  "finishColorVarianceAlpha" : 0,
  "rotationEnd" : 0,
  "startColorVarianceBlue" : 0,
  "rotatePerSecondVariance" : 0,
  "particleLifespan" : 1,
  "minRadius" : 300,
  "configName" : "windDamage1",
  "tangentialAcceleration" : 615.3542,
  "rotationStart" : 16.07556,
  "startColorVarianceGreen" : 0,
  "speed" : 718.0449,
  "minRadiusVariance" : 0,
  "finishColorVarianceBlue" : 0,
  "finishColorBlue" : 0.9998799,
  "finishColorGreen" : 1,
  "blendFuncDestination" : 772,
  "finishColorAlpha" : 0,
  "sourcePositionVariancex" : 0,
  "startParticleSize" : 50,
  "sourcePositionVariancey" : 0,
  "startColorRed" : 0.9999018,
  "finishColorVarianceRed" : 0,
  "absolutePosition" : false,
  "textureFileName" : "windDamage1.png",
  "startColorVarianceAlpha" : 1,
  "maxParticles" : 25,
  "finishColorVarianceGreen" : 0,
  "finishParticleSize" : 200,
  "duration" : 2,
  "startColorVarianceRed" : 0,
  "finishColorRed" : 0.9999018,
  "gravityx" : -663.6958,
  "maxRadiusVariance" : 0,
  "finishParticleSizeVariance" : 0,
  "gravityy" : -1540.501,
  "rotationEndVariance" : 0,
  "startColorBlue" : 0.9998799,
  "rotationStartVariance" : 37.14041,
  "speedVariance" : 0,
  "radialAccelVariance" : 228.1702,
  "textureImageData" : "",
  "tangentialAccelVariance" : -149.6504,
  "particleLifespanVariance" : 0.75,
  "angleVariance" : -15,
  "angle" : -10,
  "maxRadius" : 0
}