{
  "startColorAlpha" : 1,
  "startParticleSizeVariance" : 28.52992,
  "startColorGreen" : 0.8251349,
  "rotatePerSecond" : 20,
  "radialAcceleration" : 0,
  "yCoordFlipped" : -1,
  "emitterType" : 1,
  "blendFuncSource" : 770,
  "finishColorVarianceAlpha" : 0,
  "rotationEnd" : 0,
  "startColorVarianceBlue" : 0,
  "rotatePerSecondVariance" : -40,
  "particleLifespan" : 1,
  "minRadius" : 195.972,
  "configName" : "specialChargeIce2",
  "tangentialAcceleration" : -0,
  "rotationStart" : 0,
  "startColorVarianceGreen" : 0,
  "speed" : 196.5812,
  "minRadiusVariance" : 18,
  "finishColorVarianceBlue" : 0,
  "finishColorBlue" : 1,
  "finishColorGreen" : 1,
  "blendFuncDestination" : 771,
  "finishColorAlpha" : 0,
  "sourcePositionVariancex" : 0,
  "startParticleSize" : 5,
  "sourcePositionVariancey" : -64,
  "startColorRed" : 0.3878835,
  "finishColorVarianceRed" : 0,
  "absolutePosition" : false,
  "textureFileName" : "specialChargeIce2.png",
  "startColorVarianceAlpha" : 0.3530591,
  "maxParticles" : 100,
  "finishColorVarianceGreen" : 0,
  "finishParticleSize" : 0,
  "duration" : -1,
  "startColorVarianceRed" : 0,
  "finishColorRed" : 0.999996,
  "gravityx" : 7,
  "maxRadiusVariance" : 52.55682,
  "finishParticleSizeVariance" : 0,
  "gravityy" : -90.47,
  "rotationEndVariance" : 578.3888,
  "startColorBlue" : 1,
  "rotationStartVariance" : 0,
  "speedVariance" : 0,
  "radialAccelVariance" : 0,
  "textureImageData" : "",
  "tangentialAccelVariance" : -0,
  "particleLifespanVariance" : 0.5,
  "angleVariance" : -360,
  "angle" : -0,
  "maxRadius" : 163.2254
}